Workbook

Sheet NPC Dialogue
A1: KEY | B1: town_type | C1: town_name | D1: _npc_name | E1: keyword | F1: reply | G1: TriggersQuestion | H1: question | I1: qn_yes | J1: qn_no | K1: humility_related_flag
A2: =C2&"|"&D2&"|"&E2 -> Britain|Bartender|Black stone (20 gold) | B2: Towns | C2: Britain | D2: Bartender | E2: Black stone (20 gold) | F2: Ah, the Black Stone. Yes I’ve heard of it. But, the only one who knows where it lies is the wizard Merlin. | G2: =IF(ISNA(VLOOKUP(B2&"|"&C2&"|"&D2&"|"&E2,QuestionTriggers!A:F,6,FALSE)),"","--->")
A3: =C3&"|"&D3&"|"&E3 -> Britain|Bridge Guard|BRID | B3: Towns | C3: Britain | D3: Bridge Guard | E3: BRID | F3: Across the bridge our people dance and sing! | G3: =IF(ISNA(VLOOKUP(B3&"|"&C3&"|"&D3&"|"&E3,QuestionTriggers!A:F,6,FALSE)),"","--->") | H3: Would thou like to join them? | I3: Remember, an open heart is the first step on the path to wisdom! | J3: Then you have no business across the bridge.
A4: =C4&"|"&D4&"|"&E4 -> Britain|Bridge Guard|GUAR | B4: Towns | C4: Britain | D4: Bridge Guard | E4: GUAR | F4: Yep. | G4: =IF(ISNA(VLOOKUP(B4&"|"&C4&"|"&D4&"|"&E4,QuestionTriggers!A:F,6,FALSE)),"","--->") -> ---> | H4: Would thou like to join them? | I4: Remember, an open heart is the first step on the path to wisdom! | J4: Then you have no business across the bridge.
A5: =C5&"|"&D5&"|"&E5 -> Britain|Bridge Guard|HEALTH | B5: Towns | C5: Britain | D5: Bridge Guard | E5: HEALTH | F5: Good. | G5: =IF(ISNA(VLOOKUP(B5&"|"&C5&"|"&D5&"|"&E5,QuestionTriggers!A:F,6,FALSE)),"","--->") | H5: Would thou like to join them? | I5: Remember, an open heart is the first step on the path to wisdom! | J5: Then you have no business across the bridge.
A6: =C6&"|"&D6&"|"&E6 -> Britain|Bridge Guard|JOB | B6: Towns | C6: Britain | D6: Bridge Guard | E6: JOB | F6: I guard the bridge. | G6: =IF(ISNA(VLOOKUP(B6&"|"&C6&"|"&D6&"|"&E6,QuestionTriggers!A:F,6,FALSE)),"","--->") | H6: Would thou like to join them? | I6: Remember, an open heart is the first step on the path to wisdom! | J6: Then you have no business across the bridge.
A7: =C7&"|"&D7&"|"&E7 -> Britain|Bridge Guard|LOOK | B7: Towns | C7: Britain | D7: Bridge Guard | E7: LOOK | F7: A guard | G7: =IF(ISNA(VLOOKUP(B7&"|"&C7&"|"&D7&"|"&E7,QuestionTriggers!A:F,6,FALSE)),"","--->") | H7: Would thou like to join them? | I7: Remember, an open heart is the first step on the path to wisdom! | J7: Then you have no business across the bridge.
A8: =C8&"|"&D8&"|"&E8 -> Britain|Bridge Guard|NAME | B8: Towns | C8: Britain | D8: Bridge Guard | E8: NAME | F8: a guard | G8: =IF(ISNA(VLOOKUP(B8&"|"&C8&"|"&D8&"|"&E8,QuestionTriggers!A:F,6,FALSE)),"","--->") | H8: Would thou like to join them? | I8: Remember, an open heart is the first step on the path to wisdom! | J8: Then you have no business across the bridge.
A9: =C9&"|"&D9&"|"&E9 -> Britain|Child|COMP | B9: Towns | C9: Britain | D9: Child | E9: COMP | F9: Never care so much for thyself that thou cannot care for others! | G9: =IF(ISNA(VLOOKUP(B9&"|"&C9&"|"&D9&"|"&E9,QuestionTriggers!A:F,6,FALSE)),"","--->") -> ---> | H9: Know ye the mantra of compassion? | I9: Good. | J9: Ask Cricket!
A10: =C10&"|"&D10&"|"&E10 -> Britain|Child|HEALTH | B10: Towns | C10: Britain | D10: Child | E10: HEALTH | F10: O.K. | G10: =IF(ISNA(VLOOKUP(B10&"|"&C10&"|"&D10&"|"&E10,QuestionTriggers!A:F,6,FALSE)),"","--->") | H10: Know ye the mantra of compassion? | I10: Good. | J10: Ask Cricket!
A11: =C11&"|"&D11&"|"&E11 -> Britain|Child|JOB | B11: Towns | C11: Britain | D11: Child | E11: JOB | F11: I am learning compassion. | G11: =IF(ISNA(VLOOKUP(B11&"|"&C11&"|"&D11&"|"&E11,QuestionTriggers!A:F,6,FALSE)),"","--->") | H11: Know ye the mantra of compassion? | I11: Good. | J11: Ask Cricket!
A12: =C12&"|"&D12&"|"&E12 -> Britain|Child|LEAR | B12: Towns | C12: Britain | D12: Child | E12: LEAR | F12: The solution to ones problems often lies in solving others! | G12: =IF(ISNA(VLOOKUP(B12&"|"&C12&"|"&D12&"|"&E12,QuestionTriggers!A:F,6,FALSE)),"","--->") | H12: Know ye the mantra of compassion? | I12: Good. | J12: Ask Cricket!
A13: =C13&"|"&D13&"|"&E13 -> Britain|Child|LOOK | B13: Towns | C13: Britain | D13: Child | E13: LOOK | F13: A small child | G13: =IF(ISNA(VLOOKUP(B13&"|"&C13&"|"&D13&"|"&E13,QuestionTriggers!A:F,6,FALSE)),"","--->") | H13: Know ye the mantra of compassion? | I13: Good. | J13: Ask Cricket!
A14: =C14&"|"&D14&"|"&E14 -> Britain|Child|NAME | B14: Towns | C14: Britain | D14: Child | E14: NAME | F14: a child | G14: =IF(ISNA(VLOOKUP(B14&"|"&C14&"|"&D14&"|"&E14,QuestionTriggers!A:F,6,FALSE)),"","--->") | H14: Know ye the mantra of compassion? | I14: Good. | J14: Ask Cricket!
... A44: =C44&"|"&D44&"|"&E44 -> Britain|Joe|STON | B44: Towns | C44: Britain | D44: Joe | E44: STON | F44: The yellow stone is in the dungeon Despise... | G44: =IF(ISNA(VLOOKUP(B44&"|"&C44&"|"&D44&"|"&E44,QuestionTriggers!A:F,6,FALSE)),"","--->") | H44: Give me rum?... | I44: Thanxth... my friend Joe can help with the stones... hic... | J44: Ah, be a joe!
A45: =C45&"|"&D45&"|"&E45 -> Britain|Julio|COMP | B45: Towns | C45: Britain | D45: Julio | E45: COMP | F45: Compassion derives itself from unending love! | G45: =IF(ISNA(VLOOKUP(B45&"|"&C45&"|"&D45&"|"&E45,QuestionTriggers!A:F,6,FALSE)),"","--->") -> ---> | H45: Dost thou know the true nature of all things? | I45: Thou art a liar and a braggart. | J45: No mortal can. | K45: NO improves Humility
A46: =C46&"|"&D46&"|"&E46 -> Britain|Julio|HEALTH | B46: Towns | C46: Britain | D46: Julio | E46: HEALTH | F46: Solemn. | G46: =IF(ISNA(VLOOKUP(B46&"|"&C46&"|"&D46&"|"&E46,QuestionTriggers!A:F,6,FALSE)),"","--->") | H46: Dost thou know the true nature of all things? | I46: Thou art a liar and a braggart. | J46: No mortal can. | K46: NO improves Humility
A47: =C47&"|"&D47&"|"&E47 -> Britain|Julio|JOB | B47: Towns | C47: Britain | D47: Julio | E47: JOB | F47: I seek the true nature of things! | G47: =IF(ISNA(VLOOKUP(B47&"|"&C47&"|"&D47&"|"&E47,QuestionTriggers!A:F,6,FALSE)),"","--->") | H47: Dost thou know the true nature of all things? | I47: Thou art a liar and a braggart. | J47: No mortal can. | K47: NO improves Humility
A48: =C48&"|"&D48&"|"&E48 -> Britain|Julio|LOOK | B48: Towns | C48: Britain | D48: Julio | E48: LOOK | F48: A solemn bard. | G48: =IF(ISNA(VLOOKUP(B48&"|"&C48&"|"&D48&"|"&E48,QuestionTriggers!A:F,6,FALSE)),"","--->") | H48: Dost thou know the true nature of all things? | I48: Thou art a liar and a braggart. | J48: No mortal can. | K48: NO improves Humility
A49: =C49&"|"&D49&"|"&E49 -> Britain|Julio|NAME | B49: Towns | C49: Britain | D49: Julio | E49: NAME | F49: Julio | G49: =IF(ISNA(VLOOKUP(B49&"|"&C49&"|"&D49&"|"&E49,QuestionTriggers!A:F,6,FALSE)),"","--->") | H49: Dost thou know the true nature of all things? | I49: Thou art a liar and a braggart. | J49: No mortal can. | K49: NO improves Humility
A50: =C50&"|"&D50&"|"&E50 -> Britain|Julio|NATU | B50: Towns | C50: Britain | D50: Julio | E50: NATU | F50: All things have a true nature! | G50: =IF(ISNA(VLOOKUP(B50&"|"&C50&"|"&D50&"|"&E50,QuestionTriggers!A:F,6,FALSE)),"","--->") | H50: Dost thou know the true nature of all things? | I50: Thou art a liar and a braggart. | J50: No mortal can. | K50: NO improves Humility
A51: =C51&"|"&D51&"|"&E51 -> Britain|Mentor|HEALTH | B51: Towns | C51: Britain | D51: Mentor | E51: HEALTH | F51: I am well. | G51: =IF(ISNA(VLOOKUP(B51&"|"&C51&"|"&D51&"|"&E51,QuestionTriggers!A:F,6,FALSE)),"","--->") | H51: Art thou proud? | I51: That is not a virtue! | J51: Pride exists without truth, love, or courage! | K51: NO improves Humility
A52: =C52&"|"&D52&"|"&E52 -> Britain|Mentor|JOB | B52: Towns | C52: Britain | D52: Mentor | E52: JOB | F52: I escaped Magincia! | G52: =IF(ISNA(VLOOKUP(B52&"|"&C52&"|"&D52&"|"&E52,QuestionTriggers!A:F,6,FALSE)),"","--->") | H52: Art thou proud? | I52: That is not a virtue! | J52: Pride exists without truth, love, or courage! | K52: NO improves Humility
A53: =C53&"|"&D53&"|"&E53 -> Britain|Mentor|LOOK | B53: Towns | C53: Britain | D53: Mentor | E53: LOOK | F53: A wise shepherd. | G53: =IF(ISNA(VLOOKUP(B53&"|"&C53&"|"&D53&"|"&E53,QuestionTriggers!A:F,6,FALSE)),"","--->") | H53: Art thou proud? | I53: That is not a virtue! | J53: Pride exists without truth, love, or courage! | K53: NO improves Humility
A54: =C54&"|"&D54&"|"&E54 -> Britain|Mentor|MAGI | B54: Towns | C54: Britain | D54: Mentor | E54: MAGI | F54: Pride was too great in Magincia! | G54: =IF(ISNA(VLOOKUP(B54&"|"&C54&"|"&D54&"|"&E54,QuestionTriggers!A:F,6,FALSE)),"","--->") | H54: Art thou proud? | I54: That is not a virtue! | J54: Pride exists without truth, love, or courage! | K54: NO improves Humility
A55: =C55&"|"&D55&"|"&E55 -> Britain|Mentor|NAME | B55: Towns | C55: Britain | D55: Mentor | E55: NAME | F55: Mentor | G55: =IF(ISNA(VLOOKUP(B55&"|"&C55&"|"&D55&"|"&E55,QuestionTriggers!A:F,6,FALSE)),"","--->") | H55: Art thou proud? | I55: That is not a virtue! | J55: Pride exists without truth, love, or courage! | K55: NO improves Humility
A56: =C56&"|"&D56&"|"&E56 -> Britain|Mentor|PRID | B56: Towns | C56: Britain | D56: Mentor | E56: PRID | F56: The city was destroyed by daemons for its pride! | G56: =IF(ISNA(VLOOKUP(B56&"|"&C56&"|"&D56&"|"&E56,QuestionTriggers!A:F,6,FALSE)),"","--->") -> ---> | H56: Art thou proud? | I56: That is not a virtue! | J56: Pride exists without truth, love, or courage! | K56: NO improves Humility
A57: =C57&"|"&D57&"|"&E57 -> Britain|Pepper|BARD | B57: Towns | C57: Britain | D57: Pepper | E57: BARD | F57: Bards know many things. | G57: =IF(ISNA(VLOOKUP(B57&"|"&C57&"|"&D57&"|"&E57,QuestionTriggers!A:F,6,FALSE)),"","--->") | H57: Dost thou seek something? | I57: What might that be? | J57: Alas, I may have been able to help.
A58: =C58&"|"&D58&"|"&E58 -> Britain|Pepper|HEALTH | B58: Towns | C58: Britain | D58: Pepper | E58: HEALTH | F58: Healthy. | G58: =IF(ISNA(VLOOKUP(B58&"|"&C58&"|"&D58&"|"&E58,QuestionTriggers!A:F,6,FALSE)),"","--->") | H58: Dost thou seek something? | I58: What might that be? | J58: Alas, I may have been able to help.
A59: =C59&"|"&D59&"|"&E59 -> Britain|Pepper|JOB | B59: Towns | C59: Britain | D59: Pepper | E59: JOB | F59: I am a fighting bard. | G59: =IF(ISNA(VLOOKUP(B59&"|"&C59&"|"&D59&"|"&E59,QuestionTriggers!A:F,6,FALSE)),"","--->") | H59: Dost thou seek something? | I59: What might that be? | J59: Alas, I may have been able to help.
A60: =C60&"|"&D60&"|"&E60 -> Britain|Pepper|LOOK | B60: Towns | C60: Britain | D60: Pepper | E60: LOOK | F60: A spicy woman. | G60: =IF(ISNA(VLOOKUP(B60&"|"&C60&"|"&D60&"|"&E60,QuestionTriggers!A:F,6,FALSE)),"","--->") | H60: Dost thou seek something? | I60: What might that be? | J60: Alas, I may have been able to help.
A61: =C61&"|"&D61&"|"&E61 -> Britain|Pepper|NAME | B61: Towns | C61: Britain | D61: Pepper | E61: NAME | F61: Pepper | G61: =IF(ISNA(VLOOKUP(B61&"|"&C61&"|"&D61&"|"&E61,QuestionTriggers!A:F,6,FALSE)),"","--->") | H61: Dost thou seek something? | I61: What might that be? | J61: Alas, I may have been able to help.
A62: =C62&"|"&D62&"|"&E62 -> Britain|Pepper|RUNE | B62: Towns | C62: Britain | D62: Pepper | E62: RUNE | F62: The rune of compassion lies at the end of a hall somewhere in this towne. | G62: =IF(ISNA(VLOOKUP(B62&"|"&C62&"|"&D62&"|"&E62,QuestionTriggers!A:F,6,FALSE)),"","--->") -> ---> | H62: Dost thou seek something? | I62: What might that be? | J62: Alas, I may have been able to help.
A63: =C63&"|"&D63&"|"&E63 -> Britain|Sebastian|HEALTH | B63: Towns | C63: Britain | D63: Sebastian | E63: HEALTH | F63: Not so well. | G63: =IF(ISNA(VLOOKUP(B63&"|"&C63&"|"&D63&"|"&E63,QuestionTriggers!A:F,6,FALSE)),"","--->") | H63: Wilt thou find and destroy it? | I63: Then ask at the pub there of the skull! | J63: Oh.
A64: =C64&"|"&D64&"|"&E64 -> Britain|Sebastian|JOB | B64: Towns | C64: Britain | D64: Sebastian | E64: JOB | F64: I know a terrible secret! | G64: =IF(ISNA(VLOOKUP(B64&"|"&C64&"|"&D64&"|"&E64,QuestionTriggers!A:F,6,FALSE)),"","--->") | H64: Wilt thou find and destroy it? | I64: Then ask at the pub there of the skull! | J64: Oh.
A65: =C65&"|"&D65&"|"&E65 -> Britain|Sebastian|LOOK | B65: Towns | C65: Britain | D65: Sebastian | E65: LOOK | F65: An injured person. | G65: =IF(ISNA(VLOOKUP(B65&"|"&C65&"|"&D65&"|"&E65,QuestionTriggers!A:F,6,FALSE)),"","--->") | H65: Wilt thou find and destroy it? | I65: Then ask at the pub there of the skull! | J65: Oh.
A66: =C66&"|"&D66&"|"&E66 -> Britain|Sebastian|MOND | B66: Towns | C66: Britain | D66: Sebastian | E66: MOND | F66: An artifact remains! I heard at Buccaneer’s Den! | G66: =IF(ISNA(VLOOKUP(B66&"|"&C66&"|"&D66&"|"&E66,QuestionTriggers!A:F,6,FALSE)),"","--->") -> ---> | H66: Wilt thou find and destroy it? | I66: Then ask at the pub there of the skull! | J66: Oh.
A67: =C67&"|"&D67&"|"&E67 -> Britain|Sebastian|NAME | B67: Towns | C67: Britain | D67: Sebastian | E67: NAME | F67: Sebastian | G67: =IF(ISNA(VLOOKUP(B67&"|"&C67&"|"&D67&"|"&E67,QuestionTriggers!A:F,6,FALSE)),"","--->") | H67: Wilt thou find and destroy it? | I67: Then ask at the pub there of the skull! | J67: Oh.
A68: =C68&"|"&D68&"|"&E68 -> Britain|Sebastian|SECR | B68: Towns | C68: Britain | D68: Sebastian | E68: SECR | F68: Mondain’s influence has not left the world! | G68: =IF(ISNA(VLOOKUP(B68&"|"&C68&"|"&D68&"|"&E68,QuestionTriggers!A:F,6,FALSE)),"","--->") | H68: Wilt thou find and destroy it? | I68: Then ask at the pub there of the skull! | J68: Oh.
... A98: =C98&"|"&D98&"|"&E98 -> Britain|Thevel|ORBS | B98: Towns | C98: Britain | D98: Thevel | E98: ORBS | F98: A one-handed beggar knows their secrets! | G98: =IF(ISNA(VLOOKUP(B98&"|"&C98&"|"&D98&"|"&E98,QuestionTriggers!A:F,6,FALSE)),"","--->") | H98: Hast thou seen him? | I98: Only he knows the orb’s gift! | J98: Find him in Serpent castle for he knows of orbs!
A99: =C99&"|"&D99&"|"&E99 -> Bucaneer's Den|Bartender|Skull (99 gold) | B99: Villages | C99: Bucaneer's Den | D99: Bartender | E99: Skull (99 gold) | F99: If thou must know of that evilest of all things... find the beggar Jude. He is very very poor! | G99: =IF(ISNA(VLOOKUP(B99&"|"&C99&"|"&D99&"|"&E99,QuestionTriggers!A:F,6,FALSE)),"","--->")
A100: =C100&"|"&D100&"|"&E100 -> Buccaneer’s Den|Boris|HEALTH | B100: Villages | C100: Buccaneer’s Den | D100: Boris | E100: HEALTH | F100: Good’n smelly. | G100: =IF(ISNA(VLOOKUP(B100&"|"&C100&"|"&D100&"|"&E100,QuestionTriggers!A:F,6,FALSE)),"","--->") | H100: Dost thou need such an item? | I100: I just gave the guild shop a new supply! | J100: Ah well, maybe next time.
A101: =C101&"|"&D101&"|"&E101 -> Buccaneer’s Den|Boris|ITEM | B101: Villages | C101: Buccaneer’s Den | D101: Boris | E101: ITEM | F101: Magic keys, magic gems, that sort of thing. | G101: =IF(ISNA(VLOOKUP(B101&"|"&C101&"|"&D101&"|"&E101,QuestionTriggers!A:F,6,FALSE)),"","--->") -> ---> | H101: Dost thou need such an item? | I101: I just gave the guild shop a new supply! | J101: Ah well, maybe next time.
A102: =C102&"|"&D102&"|"&E102 -> Buccaneer’s Den|Boris|JOB | B102: Villages | C102: Buccaneer’s Den | D102: Boris | E102: JOB | F102: I smuggle black market items. | G102: =IF(ISNA(VLOOKUP(B102&"|"&C102&"|"&D102&"|"&E102,QuestionTriggers!A:F,6,FALSE)),"","--->") | H102: Dost thou need such an item? | I102: I just gave the guild shop a new supply! | J102: Ah well, maybe next time.
A103: =C103&"|"&D103&"|"&E103 -> Buccaneer’s Den|Boris|LOOK | B103: Villages | C103: Buccaneer’s Den | D103: Boris | E103: LOOK | F103: An ugly orc! | G103: =IF(ISNA(VLOOKUP(B103&"|"&C103&"|"&D103&"|"&E103,QuestionTriggers!A:F,6,FALSE)),"","--->") | H103: Dost thou need such an item? | I103: I just gave the guild shop a new supply! | J103: Ah well, maybe next time.
A104: =C104&"|"&D104&"|"&E104 -> Buccaneer’s Den|Boris|NAME | B104: Villages | C104: Buccaneer’s Den | D104: Boris | E104: NAME | F104: Boris | G104: =IF(ISNA(VLOOKUP(B104&"|"&C104&"|"&D104&"|"&E104,QuestionTriggers!A:F,6,FALSE)),"","--->") | H104: Dost thou need such an item? | I104: I just gave the guild shop a new supply! | J104: Ah well, maybe next time.
A105: =C105&"|"&D105&"|"&E105 -> Buccaneer’s Den|Brigant|HEALTH | B105: Villages | C105: Buccaneer’s Den | D105: Brigant | E105: HEALTH | F105: Shove it! | G105: =IF(ISNA(VLOOKUP(B105&"|"&C105&"|"&D105&"|"&E105,QuestionTriggers!A:F,6,FALSE)),"","--->") | H105: Did thou hear me? | I105: Then do it! | J105: I said shove it!
A106: =C106&"|"&D106&"|"&E106 -> Buccaneer’s Den|Brigant|IT | B106: Villages | C106: Buccaneer’s Den | D106: Brigant | E106: IT | F106: Thy face! A A | G106: =IF(ISNA(VLOOKUP(B106&"|"&C106&"|"&D106&"|"&E106,QuestionTriggers!A:F,6,FALSE)),"","--->") -> ---> | H106: Did thou hear me? | I106: Then do it! | J106: I said shove it!
A107: =C107&"|"&D107&"|"&E107 -> Buccaneer’s Den|Brigant|JOB | B107: Villages | C107: Buccaneer’s Den | D107: Brigant | E107: JOB | F107: Aw, buzz off! | G107: =IF(ISNA(VLOOKUP(B107&"|"&C107&"|"&D107&"|"&E107,QuestionTriggers!A:F,6,FALSE)),"","--->") | H107: Did thou hear me? | I107: Then do it! | J107: I said shove it!
A108: =C108&"|"&D108&"|"&E108 -> Buccaneer’s Den|Brigant|LOOK | B108: Villages | C108: Buccaneer’s Den | D108: Brigant | E108: LOOK | F108: A big fat troll. | G108: =IF(ISNA(VLOOKUP(B108&"|"&C108&"|"&D108&"|"&E108,QuestionTriggers!A:F,6,FALSE)),"","--->") | H108: Did thou hear me? | I108: Then do it! | J108: I said shove it!
A109: =C109&"|"&D109&"|"&E109 -> Buccaneer’s Den|Brigant|NAME | B109: Villages | C109: Buccaneer’s Den | D109: Brigant | E109: NAME | F109: Brigant | G109: =IF(ISNA(VLOOKUP(B109&"|"&C109&"|"&D109&"|"&E109,QuestionTriggers!A:F,6,FALSE)),"","--->") | H109: Did thou hear me? | I109: Then do it! | J109: I said shove it!
A110: =C110&"|"&D110&"|"&E110 -> Buccaneer’s Den|Dancek|HEALTH | B110: Villages | C110: Buccaneer’s Den | D110: Dancek | E110: HEALTH | F110: Jolly good, thanks. | G110: =IF(ISNA(VLOOKUP(B110&"|"&C110&"|"&D110&"|"&E110,QuestionTriggers!A:F,6,FALSE)),"","--->") | H110: Dost thou own a ship! | I110: Good odds I built the cannons! | J110: Thou really should get one!
A111: =C111&"|"&D111&"|"&E111 -> Buccaneer’s Den|Dancek|JOB | B111: Villages | C111: Buccaneer’s Den | D111: Dancek | E111: JOB | F111: I am a tinker by trade. | G111: =IF(ISNA(VLOOKUP(B111&"|"&C111&"|"&D111&"|"&E111,QuestionTriggers!A:F,6,FALSE)),"","--->") | H111: Dost thou own a ship! | I111: Good odds I built the cannons! | J111: Thou really should get one!
... A167: =C167&"|"&D167&"|"&E167 -> Buccaneer’s Den|Seanna|SLEE | B167: Villages | C167: Buccaneer’s Den | D167: Seanna | E167: SLEE | F167: A sleep spell requires but one part silk! sleep... sleep... sleep... | G167: =IF(ISNA(VLOOKUP(B167&"|"&C167&"|"&D167&"|"&E167,QuestionTriggers!A:F,6,FALSE)),"","--->") -> ---> | H167: My dear friend, may I help you? | I167: How about with thy magic? | J167: Ah
A168: =C168&"|"&D168&"|"&E168 -> Buccaneer’s Den|Silver John|HEALTH | B168: Villages | C168: Buccaneer’s Den | D168: Silver John | E168: HEALTH | F168: Good enough, eh! | G168: =IF(ISNA(VLOOKUP(B168&"|"&C168&"|"&D168&"|"&E168,QuestionTriggers!A:F,6,FALSE)),"","--->") | H168: Art thou a pirate? | I168: Good matey! | J168: Thou had best leave this place ’fore there’s any trouble! | K168: NO improves Humility
A169: =C169&"|"&D169&"|"&E169 -> Buccaneer’s Den|Silver John|JOB | B169: Villages | C169: Buccaneer’s Den | D169: Silver John | E169: JOB | F169: I’m a pirate matey! | G169: =IF(ISNA(VLOOKUP(B169&"|"&C169&"|"&D169&"|"&E169,QuestionTriggers!A:F,6,FALSE)),"","--->") | H169: Art thou a pirate? | I169: Good matey! | J169: Thou had best leave this place ’fore there’s any trouble! | K169: NO improves Humility
A170: =C170&"|"&D170&"|"&E170 -> Buccaneer’s Den|Silver John|LOOK | B170: Villages | C170: Buccaneer’s Den | D170: Silver John | E170: LOOK | F170: A tall sailor. | G170: =IF(ISNA(VLOOKUP(B170&"|"&C170&"|"&D170&"|"&E170,QuestionTriggers!A:F,6,FALSE)),"","--->") | H170: Art thou a pirate? | I170: Good matey! | J170: Thou had best leave this place ’fore there’s any trouble! | K170: NO improves Humility
A171: =C171&"|"&D171&"|"&E171 -> Buccaneer’s Den|Silver John|NAME | B171: Villages | C171: Buccaneer’s Den | D171: Silver John | E171: NAME | F171: Silver John | G171: =IF(ISNA(VLOOKUP(B171&"|"&C171&"|"&D171&"|"&E171,QuestionTriggers!A:F,6,FALSE)),"","--->") | H171: Art thou a pirate? | I171: Good matey! | J171: Thou had best leave this place ’fore there’s any trouble! | K171: NO improves Humility
A172: =C172&"|"&D172&"|"&E172 -> Buccaneer’s Den|Silver John|PIRA | B172: Villages | C172: Buccaneer’s Den | D172: Silver John | E172: PIRA | F172: We raid the coasts of Britannia, fun eh! | G172: =IF(ISNA(VLOOKUP(B172&"|"&C172&"|"&D172&"|"&E172,QuestionTriggers!A:F,6,FALSE)),"","--->") | H172: Art thou a pirate? | I172: Good matey! | J172: Thou had best leave this place ’fore there’s any trouble! | K172: NO improves Humility
A173: =C173&"|"&D173&"|"&E173 -> Buccaneer’s Den|Silver John|RAID | B173: Villages | C173: Buccaneer’s Den | D173: Silver John | E173: RAID | F173: Pillage and burn! | G173: =IF(ISNA(VLOOKUP(B173&"|"&C173&"|"&D173&"|"&E173,QuestionTriggers!A:F,6,FALSE)),"","--->") -> ---> | H173: Art thou a pirate? | I173: Good matey! | J173: Thou had best leave this place ’fore there’s any trouble! | K173: NO improves Humility
A174: =C174&"|"&D174&"|"&E174 -> Buccaneer’s Den|Slysam|CLEV | B174: Villages | C174: Buccaneer’s Den | D174: Slysam | E174: CLEV | F174: Thou dost ask too many questions! | G174: =IF(ISNA(VLOOKUP(B174&"|"&C174&"|"&D174&"|"&E174,QuestionTriggers!A:F,6,FALSE)),"","--->") -> ---> | H174: Art thou a thief? | I174: Oh, I’d better watch out! | J174: Just as I thought
A175: =C175&"|"&D175&"|"&E175 -> Buccaneer’s Den|Slysam|HEALTH | B175: Villages | C175: Buccaneer’s Den | D175: Slysam | E175: HEALTH | F175: As good as I need be! | G175: =IF(ISNA(VLOOKUP(B175&"|"&C175&"|"&D175&"|"&E175,QuestionTriggers!A:F,6,FALSE)),"","--->") | H175: Art thou a thief? | I175: Oh, I’d better watch out! | J175: Just as I thought
A176: =C176&"|"&D176&"|"&E176 -> Buccaneer’s Den|Slysam|JOB | B176: Villages | C176: Buccaneer’s Den | D176: Slysam | E176: JOB | F176: What’s it to thee? | G176: =IF(ISNA(VLOOKUP(B176&"|"&C176&"|"&D176&"|"&E176,QuestionTriggers!A:F,6,FALSE)),"","--->") | H176: Art thou a thief? | I176: Oh, I’d better watch out! | J176: Just as I thought
A177: =C177&"|"&D177&"|"&E177 -> Buccaneer’s Den|Slysam|LOOK | B177: Villages | C177: Buccaneer’s Den | D177: Slysam | E177: LOOK | F177: A nimble thief. | G177: =IF(ISNA(VLOOKUP(B177&"|"&C177&"|"&D177&"|"&E177,QuestionTriggers!A:F,6,FALSE)),"","--->") | H177: Art thou a thief? | I177: Oh, I’d better watch out! | J177: Just as I thought
A178: =C178&"|"&D178&"|"&E178 -> Buccaneer’s Den|Slysam|NAME | B178: Villages | C178: Buccaneer’s Den | D178: Slysam | E178: NAME | F178: Slysam | G178: =IF(ISNA(VLOOKUP(B178&"|"&C178&"|"&D178&"|"&E178,QuestionTriggers!A:F,6,FALSE)),"","--->") | H178: Art thou a thief? | I178: Oh, I’d better watch out! | J178: Just as I thought
A179: =C179&"|"&D179&"|"&E179 -> Buccaneer’s Den|Slysam|THIE | B179: Villages | C179: Buccaneer’s Den | D179: Slysam | E179: THIE | F179: Yea, and clever too. | G179: =IF(ISNA(VLOOKUP(B179&"|"&C179&"|"&D179&"|"&E179,QuestionTriggers!A:F,6,FALSE)),"","--->") | H179: Art thou a thief? | I179: Oh, I’d better watch out! | J179: Just as I thought
A180: =C180&"|"&D180&"|"&E180 -> Buccaneer’s Den|Sniflet|HEALTH | B180: Villages | C180: Buccaneer’s Den | D180: Sniflet | E180: HEALTH | F180: O.K. for now. | G180: =IF(ISNA(VLOOKUP(B180&"|"&C180&"|"&D180&"|"&E180,QuestionTriggers!A:F,6,FALSE)),"","--->") | H180: Wilt thou promise to use it only to aid the powers of good? | I180: The lighter than air device that was stolen lies near the dungeon Hythloth! | J180: Oh, no.
A181: =C181&"|"&D181&"|"&E181 -> Buccaneer’s Den|Sniflet|HIDE | B181: Villages | C181: Buccaneer’s Den | D181: Sniflet | E181: HIDE | F181: I know something others want! | G181: =IF(ISNA(VLOOKUP(B181&"|"&C181&"|"&D181&"|"&E181,QuestionTriggers!A:F,6,FALSE)),"","--->") | H181: Wilt thou promise to use it only to aid the powers of good? | I181: The lighter than air device that was stolen lies near the dungeon Hythloth! | J181: Oh, no.
A182: =C182&"|"&D182&"|"&E182 -> Buccaneer’s Den|Sniflet|JOB | B182: Villages | C182: Buccaneer’s Den | D182: Sniflet | E182: JOB | F182: I am hiding. | G182: =IF(ISNA(VLOOKUP(B182&"|"&C182&"|"&D182&"|"&E182,QuestionTriggers!A:F,6,FALSE)),"","--->") | H182: Wilt thou promise to use it only to aid the powers of good? | I182: The lighter than air device that was stolen lies near the dungeon Hythloth! | J182: Oh, no.
A183: =C183&"|"&D183&"|"&E183 -> Buccaneer’s Den|Sniflet|LOOK | B183: Villages | C183: Buccaneer’s Den | D183: Sniflet | E183: LOOK | F183: A cowering man. | G183: =IF(ISNA(VLOOKUP(B183&"|"&C183&"|"&D183&"|"&E183,QuestionTriggers!A:F,6,FALSE)),"","--->") | H183: Wilt thou promise to use it only to aid the powers of good? | I183: The lighter than air device that was stolen lies near the dungeon Hythloth! | J183: Oh, no.
A184: =C184&"|"&D184&"|"&E184 -> Buccaneer’s Den|Sniflet|NAME | B184: Villages | C184: Buccaneer’s Den | D184: Sniflet | E184: NAME | F184: Sniflet | G184: =IF(ISNA(VLOOKUP(B184&"|"&C184&"|"&D184&"|"&E184,QuestionTriggers!A:F,6,FALSE)),"","--->") | H184: Wilt thou promise to use it only to aid the powers of good? | I184: The lighter than air device that was stolen lies near the dungeon Hythloth! | J184: Oh, no.
A185: =C185&"|"&D185&"|"&E185 -> Buccaneer’s Den|Sniflet|SOME | B185: Villages | C185: Buccaneer’s Den | D185: Sniflet | E185: SOME | F185: I... I... | G185: =IF(ISNA(VLOOKUP(B185&"|"&C185&"|"&D185&"|"&E185,QuestionTriggers!A:F,6,FALSE)),"","--->") -> ---> | H185: Wilt thou promise to use it only to aid the powers of good? | I185: The lighter than air device that was stolen lies near the dungeon Hythloth! | J185: Oh, no.
... A203: =C203&"|"&D203&"|"&E203 -> Castle Britannia|Gate Guard|NAME | B203: Castles | C203: Castle Britannia | D203: Gate Guard | E203: NAME | F203: a guard | G203: =IF(ISNA(VLOOKUP(B203&"|"&C203&"|"&D203&"|"&E203,QuestionTriggers!A:F,6,FALSE)),"","--->") | H203: Do you seek Lord British? | I203: He is on the upper level in the throne room. | J203: He will aid you if you are in need!
A204: =C204&"|"&D204&"|"&E204 -> Castle Britannia|Guard (2nd Floor)|GUAR | B204: Castles | C204: Castle Britannia | D204: Guard (2nd Floor) | E204: GUAR | F204: A guard must be a valiant warrior! | G204: =IF(ISNA(VLOOKUP(B204&"|"&C204&"|"&D204&"|"&E204,QuestionTriggers!A:F,6,FALSE)),"","--->") -> ---> | H204: Art thou the most valiant warrior? | I204: Then thou should be a guard! | J204: Still flee not from battle! | K204: NO improves Humility
A205: =C205&"|"&D205&"|"&E205 -> Castle Britannia|Guard (2nd Floor)|HEALTH | B205: Castles | C205: Castle Britannia | D205: Guard (2nd Floor) | E205: HEALTH | F205: Great! | G205: =IF(ISNA(VLOOKUP(B205&"|"&C205&"|"&D205&"|"&E205,QuestionTriggers!A:F,6,FALSE)),"","--->") | H205: Art thou the most valiant warrior? | I205: Then thou should be a guard! | J205: Still flee not from battle! | K205: NO improves Humility
A206: =C206&"|"&D206&"|"&E206 -> Castle Britannia|Guard (2nd Floor)|JOB | B206: Castles | C206: Castle Britannia | D206: Guard (2nd Floor) | E206: JOB | F206: I guard the castle and my liege! | G206: =IF(ISNA(VLOOKUP(B206&"|"&C206&"|"&D206&"|"&E206,QuestionTriggers!A:F,6,FALSE)),"","--->") | H206: Art thou the most valiant warrior? | I206: Then thou should be a guard! | J206: Still flee not from battle! | K206: NO improves Humility
A207: =C207&"|"&D207&"|"&E207 -> Castle Britannia|Guard (2nd Floor)|LIEG | B207: Castles | C207: Castle Britannia | D207: Guard (2nd Floor) | E207: LIEG | F207: I serve Lord British! | G207: =IF(ISNA(VLOOKUP(B207&"|"&C207&"|"&D207&"|"&E207,QuestionTriggers!A:F,6,FALSE)),"","--->") | H207: Art thou the most valiant warrior? | I207: Then thou should be a guard! | J207: Still flee not from battle! | K207: NO improves Humility
A208: =C208&"|"&D208&"|"&E208 -> Castle Britannia|Guard (2nd Floor)|LOOK | B208: Castles | C208: Castle Britannia | D208: Guard (2nd Floor) | E208: LOOK | F208: A burly guard | G208: =IF(ISNA(VLOOKUP(B208&"|"&C208&"|"&D208&"|"&E208,QuestionTriggers!A:F,6,FALSE)),"","--->") | H208: Art thou the most valiant warrior? | I208: Then thou should be a guard! | J208: Still flee not from battle! | K208: NO improves Humility
A209: =C209&"|"&D209&"|"&E209 -> Castle Britannia|Guard (2nd Floor)|NAME | B209: Castles | C209: Castle Britannia | D209: Guard (2nd Floor) | E209: NAME | F209: a guard | G209: =IF(ISNA(VLOOKUP(B209&"|"&C209&"|"&D209&"|"&E209,QuestionTriggers!A:F,6,FALSE)),"","--->") | H209: Art thou the most valiant warrior? | I209: Then thou should be a guard! | J209: Still flee not from battle! | K209: NO improves Humility
A210: =C210&"|"&D210&"|"&E210 -> Castle Britannia|Hawkwind|Compassion | B210: Castles | C210: Castle Britannia | D210: Hawkwind | E210: Compassion | F210: Thou art a cold and cruel brute. Thou should go to prison for thy crimes! Thou dost kill where there is no need and give too little unto others! Thou hast not shown thy compassion well. Be more kind unto others! Thou dost show thy compassion well. Continued good will should be thy guide! Compassion is a virtue that thou hast shown well. Seek ye now Elevation! | G210: =IF(ISNA(VLOOKUP(B210&"|"&C210&"|"&D210&"|"&E210,QuestionTriggers!A:F,6,FALSE)),"","--->")
A211: =C211&"|"&D211&"|"&E211 -> Castle Britannia|Hawkwind|Honesty | B211: Castles | C211: Castle Britannia | D211: Hawkwind | E211: Honesty | F211: Thou art a thief and a scoundrel. Thou may not ever become an Avatar! Thou art not an honest soul. Thou must live a more honest life to be an Avatar! Thou hast made little progress on the paths of Honesty. Strive to prove thy worth! Thou dost seem an honest soul. Continued honesty will reward thee! Thou art truly an honest soul. Seek ye now to reach Elevation! | G211: =IF(ISNA(VLOOKUP(B211&"|"&C211&"|"&D211&"|"&E211,QuestionTriggers!A:F,6,FALSE)),"","--->")
A212: =C212&"|"&D212&"|"&E212 -> Castle Britannia|Hawkwind|Honor | B212: Castles | C212: Castle Britannia | D212: Hawkwind | E212: Honor | F212: Thou art a cad and a bounder. Thy presence is an affront. Thou art low as a slug! Thou dost not fight with honor but with malice and deceit! Thou dost need to show thyself to be more honorable. The path lies before thee! Thou dost seem to be Honorable in nature. Seek to bring Honor upon others as well! Thou hast proven thyself to be Honorable. Seek ye now for the Elevation! | G212: =IF(ISNA(VLOOKUP(B212&"|"&C212&"|"&D212&"|"&E212,QuestionTriggers!A:F,6,FALSE)),"","--->")
A213: =C213&"|"&D213&"|"&E213 -> Castle Britannia|Hawkwind|Humility | B213: Castles | C213: Castle Britannia | D213: Hawkwind | E213: Humility | F213: Thou art proud and vain. All other virtue in thee is a loss! Thou art too proud of thy little deeds. Humility is the root of all Virtue! Thy progress on this path is most uncertain. Without Humility thou art empty! Thou dost seem a humble soul. Thou art setting strong stones to build virtues upon! Thy Humility shines bright upon they being. Seek ye now for Elevation! | G213: =IF(ISNA(VLOOKUP(B213&"|"&C213&"|"&D213&"|"&E213,QuestionTriggers!A:F,6,FALSE)),"","--->")
A214: =C214&"|"&D214&"|"&E214 -> Castle Britannia|Hawkwind|Justice | B214: Castles | C214: Castle Britannia | D214: Hawkwind | E214: Justice | F214: Thou art an unjust wretch. Thou are a fulsome meddler! Thou art cruel and unjust. in time thou will suffer for thy crimes! Thou hast not proven thyself to be just. Strive to do justice unto all things! Thou dost seem fair and just. Strive to uphold Justice even more sternly! Thou art just and fair. Seek ye now the Elevation! | G214: =IF(ISNA(VLOOKUP(B214&"|"&C214&"|"&D214&"|"&E214,QuestionTriggers!A:F,6,FALSE)),"","--->")
A215: =C215&"|"&D215&"|"&E215 -> Castle Britannia|Hawkwind|Other When asked about any virtue for which Partial Avatarhood has been attained: | B215: Castles | C215: Castle Britannia | D215: Hawkwind | E215: Other When asked about any virtue for which Partial Avatarhood has been attained: | F215: Thou hast become a partial Avatar in that attribute. Thou need not my insights. | G215: =IF(ISNA(VLOOKUP(B215&"|"&C215&"|"&D215&"|"&E215,QuestionTriggers!A:F,6,FALSE)),"","--->")
A216: =C216&"|"&D216&"|"&E216 -> Castle Britannia|Hawkwind|Sacrifice | B216: Castles | C216: Castle Britannia | D216: Hawkwind | E216: Sacrifice | F216: Thou art a self-serving Tufthunter. Thou deservest not my help, yet I grant it! Thou dost need to think more of the life of others and less of thy own! Thy sacrifice is small. Give of thy life’s blood so that others may live. Thou art giving of thyself in some ways. Seek ye now to find yet more! Thy self-sacrifice is great. Seek now Elevation! | G216: =IF(ISNA(VLOOKUP(B216&"|"&C216&"|"&D216&"|"&E216,QuestionTriggers!A:F,6,FALSE)),"","--->")
A217: =C217&"|"&D217&"|"&E217 -> Castle Britannia|Hawkwind|Spirituality | B217: Castles | C217: Castle Britannia | D217: Hawkwind | E217: Spirituality | F217: Thy spirit is weak and feeble. Thou dost not strive for Perfection! Thou dost not take time to care about thy inner being, a must to be an Avatar! Strive to know and master more of thine inner being. Meditation lights the path! Thou art doing well on the path to inner sight continue to seek the inner light. Spirituality is in thy nature. Seek ye now the Elevation! | G217: =IF(ISNA(VLOOKUP(B217&"|"&C217&"|"&D217&"|"&E217,QuestionTriggers!A:F,6,FALSE)),"","--->")
A218: =C218&"|"&D218&"|"&E218 -> Castle Britannia|Hawkwind|Valor | B218: Castles | C218: Castle Britannia | D218: Hawkwind | E218: Valor | F218: Thou art a coward, thou dost flee from the hint of danger! Thou dost not display a great deal of Valor. Thou dost flee before the need! Thou art not yet a valiant warrior. Fight to defeat evil and prove thyself! Thou art showing Valor in the face of danger. Strive to become yet more so! Thou art a truly valiant warrior. Seek ye now Elevation in the virtue of valor! | G218: =IF(ISNA(VLOOKUP(B218&"|"&C218&"|"&D218&"|"&E218,QuestionTriggers!A:F,6,FALSE)),"","--->")
A219: =C219&"|"&D219&"|"&E219 -> Castle Britannia|Jester Twins|BARD | B219: Castles | C219: Castle Britannia | D219: Jester Twins | E219: BARD | F219: Our bard is very good. | G219: =IF(ISNA(VLOOKUP(B219&"|"&C219&"|"&D219&"|"&E219,QuestionTriggers!A:F,6,FALSE)),"","--->") -> ---> | H219: Dost thou like the music? | I219: Then you should go to Britain for there lives the best! | J219: A shame, we do!
A220: =C220&"|"&D220&"|"&E220 -> Castle Britannia|Jester Twins|HEALTH | B220: Castles | C220: Castle Britannia | D220: Jester Twins | E220: HEALTH | F220: Perfectly hoppy! | G220: =IF(ISNA(VLOOKUP(B220&"|"&C220&"|"&D220&"|"&E220,QuestionTriggers!A:F,6,FALSE)),"","--->") | H220: Dost thou like the music? | I220: Then you should go to Britain for there lives the best! | J220: A shame, we do!
A221: =C221&"|"&D221&"|"&E221 -> Castle Britannia|Jester Twins|JEST | B221: Castles | C221: Castle Britannia | D221: Jester Twins | E221: JEST | F221: A jester needs a good bard! | G221: =IF(ISNA(VLOOKUP(B221&"|"&C221&"|"&D221&"|"&E221,QuestionTriggers!A:F,6,FALSE)),"","--->") | H221: Dost thou like the music? | I221: Then you should go to Britain for there lives the best! | J221: A shame, we do!
A222: =C222&"|"&D222&"|"&E222 -> Castle Britannia|Jester Twins|JOB | B222: Castles | C222: Castle Britannia | D222: Jester Twins | E222: JOB | F222: To entertain. | G222: =IF(ISNA(VLOOKUP(B222&"|"&C222&"|"&D222&"|"&E222,QuestionTriggers!A:F,6,FALSE)),"","--->") | H222: Dost thou like the music? | I222: Then you should go to Britain for there lives the best! | J222: A shame, we do!
A223: =C223&"|"&D223&"|"&E223 -> Castle Britannia|Jester Twins|LOOK | B223: Castles | C223: Castle Britannia | D223: Jester Twins | E223: LOOK | F223: A dancing jester | G223: =IF(ISNA(VLOOKUP(B223&"|"&C223&"|"&D223&"|"&E223,QuestionTriggers!A:F,6,FALSE)),"","--->") | H223: Dost thou like the music? | I223: Then you should go to Britain for there lives the best! | J223: A shame, we do!
A224: =C224&"|"&D224&"|"&E224 -> Castle Britannia|Jester Twins|NAME | B224: Castles | C224: Castle Britannia | D224: Jester Twins | E224: NAME | F224: Jester Twin | G224: =IF(ISNA(VLOOKUP(B224&"|"&C224&"|"&D224&"|"&E224,QuestionTriggers!A:F,6,FALSE)),"","--->") | H224: Dost thou like the music? | I224: Then you should go to Britain for there lives the best! | J224: A shame, we do!
A225: =C225&"|"&D225&"|"&E225 -> Castle Britannia|Joshua|HEALTH | B225: Castles | C225: Castle Britannia | D225: Joshua | E225: HEALTH | F225: Well. | G225: =IF(ISNA(VLOOKUP(B225&"|"&C225&"|"&D225&"|"&E225,QuestionTriggers!A:F,6,FALSE)),"","--->") | H225: More? | I225: What one thing creates and is created by all truths, all love & all courage? | J225: Oh.
A226: =C226&"|"&D226&"|"&E226 -> Castle Britannia|Joshua|HELP | B226: Castles | C226: Castle Britannia | D226: Joshua | E226: HELP | F226: The riddle! | G226: =IF(ISNA(VLOOKUP(B226&"|"&C226&"|"&D226&"|"&E226,QuestionTriggers!A:F,6,FALSE)),"","--->") | H226: More? | I226: What one thing creates and is created by all truths, all love & all courage? | J226: Oh.
A227: =C227&"|"&D227&"|"&E227 -> Castle Britannia|Joshua|JOB | B227: Castles | C227: Castle Britannia | D227: Joshua | E227: JOB | F227: I can help. | G227: =IF(ISNA(VLOOKUP(B227&"|"&C227&"|"&D227&"|"&E227,QuestionTriggers!A:F,6,FALSE)),"","--->") | H227: More? | I227: What one thing creates and is created by all truths, all love & all courage? | J227: Oh.
A228: =C228&"|"&D228&"|"&E228 -> Castle Britannia|Joshua|LOOK | B228: Castles | C228: Castle Britannia | D228: Joshua | E228: LOOK | F228: A wise mage. | G228: =IF(ISNA(VLOOKUP(B228&"|"&C228&"|"&D228&"|"&E228,QuestionTriggers!A:F,6,FALSE)),"","--->") | H228: More? | I228: What one thing creates and is created by all truths, all love & all courage? | J228: Oh.
A229: =C229&"|"&D229&"|"&E229 -> Castle Britannia|Joshua|NAME | B229: Castles | C229: Castle Britannia | D229: Joshua | E229: NAME | F229: Joshua | G229: =IF(ISNA(VLOOKUP(B229&"|"&C229&"|"&D229&"|"&E229,QuestionTriggers!A:F,6,FALSE)),"","--->") | H229: More? | I229: What one thing creates and is created by all truths, all love & all courage? | J229: Oh.
A230: =C230&"|"&D230&"|"&E230 -> Castle Britannia|Joshua|RIDD | B230: Castles | C230: Castle Britannia | D230: Joshua | E230: RIDD | F230: If the eight philosophies of avatarhood combine into and are made from truth, love & courage... | G230: =IF(ISNA(VLOOKUP(B230&"|"&C230&"|"&D230&"|"&E230,QuestionTriggers!A:F,6,FALSE)),"","--->") -> ---> | H230: More? | I230: What one thing creates and is created by all truths, all love & all courage? | J230: Oh.
...

Sheet MC-NPC_TAGS
A1: _town_name | B1: npc_name | C1: LOOK_value | D1: MC Profession | E1: Name-the-NPC | F1: InvisiTag-the-NPC | H1: NPC TAG
A2: Moonglow | B2: Browning | C2: =VLOOKUP(A2&"|"&B2&"|"&"LOOK",'NPC Dialogue'!$A:$F,6,FALSE) -> A tall mage. | E2: ="/data merge entity @e[type=minecraft:villager,limit=1,sort=nearest] {CustomName:"""&B2&"""}" -> /data merge entity @e[type=minecraft:villager,limit=1,sort=nearest] {CustomName:"Browning"} | F2: ="/tag @e[type=minecraft:villager,name="""&B2&""",limit=1] add npc_"&LOWER(B2) -> /tag @e[type=minecraft:villager,name="Browning",limit=1] add npc_browning
A3: Moonglow | B3: Calabrini | C3: =VLOOKUP(A3&"|"&B3&"|"&"LOOK",'NPC Dialogue'!$A:$F,6,FALSE) -> A tall mage. | E3: ="/data merge entity @e[type=minecraft:villager,limit=1,sort=nearest] {CustomName:"""&B3&"""}" -> /data merge entity @e[type=minecraft:villager,limit=1,sort=nearest] {CustomName:"Calabrini"} | F3: ="/tag @e[type=minecraft:villager,name="""&B3&""",limit=1] add npc_"&LOWER(B3) -> /tag @e[type=minecraft:villager,name="Calabrini",limit=1] add npc_calabrini
A4: Moonglow | B4: Christen | C4: =VLOOKUP(A4&"|"&B4&"|"&"LOOK",'NPC Dialogue'!$A:$F,6,FALSE) -> The housekeeping nitwit. | E4: ="/data merge entity @e[type=minecraft:villager,limit=1,sort=nearest] {CustomName:"""&B4&"""}" -> /data merge entity @e[type=minecraft:villager,limit=1,sort=nearest] {CustomName:"Christen"} | F4: ="/tag @e[type=minecraft:villager,name="""&B4&""",limit=1] add npc_"&LOWER(B4) -> /tag @e[type=minecraft:villager,name="Christen",limit=1] add npc_christen
A5: Moonglow | B5: Cosima | C5: =VLOOKUP(A5&"|"&B5&"|"&"LOOK",'NPC Dialogue'!$A:$F,6,FALSE) -> An elderly woman | E5: ="/data merge entity @e[type=minecraft:villager,limit=1,sort=nearest] {CustomName:"""&B5&"""}" -> /data merge entity @e[type=minecraft:villager,limit=1,sort=nearest] {CustomName:"Cosima"} | F5: ="/tag @e[type=minecraft:villager,name="""&B5&""",limit=1] add npc_"&LOWER(B5) -> /tag @e[type=minecraft:villager,name="Cosima",limit=1] add npc_cosima
A6: Moonglow | B6: Cromwell | C6: =VLOOKUP(A6&"|"&B6&"|"&"LOOK",'NPC Dialogue'!$A:$F,6,FALSE) -> I am a regal palladin. | E6: ="/data merge entity @e[type=minecraft:villager,limit=1,sort=nearest] {CustomName:"""&B6&"""}" -> /data merge entity @e[type=minecraft:villager,limit=1,sort=nearest] {CustomName:"Cromwell"} | F6: ="/tag @e[type=minecraft:villager,name="""&B6&""",limit=1] add npc_"&LOWER(B6) -> /tag @e[type=minecraft:villager,name="Cromwell",limit=1] add npc_cromwell
A7: Moonglow | B7: Daranor | C7: =VLOOKUP(A7&"|"&B7&"|"&"LOOK",'NPC Dialogue'!$A:$F,6,FALSE) -> A hunched, insane looking man! | E7: ="/data merge entity @e[type=minecraft:villager,limit=1,sort=nearest] {CustomName:"""&B7&"""}" -> /data merge entity @e[type=minecraft:villager,limit=1,sort=nearest] {CustomName:"Daranor"} | F7: ="/tag @e[type=minecraft:villager,name="""&B7&""",limit=1] add npc_"&LOWER(B7) -> /tag @e[type=minecraft:villager,name="Daranor",limit=1] add npc_daranor
A8: Moonglow | B8: Dekker | C8: =VLOOKUP(A8&"|"&B8&"|"&"LOOK",'NPC Dialogue'!$A:$F,6,FALSE) -> A bouncy jester | E8: ="/data merge entity @e[type=minecraft:villager,limit=1,sort=nearest] {CustomName:"""&B8&"""}" -> /data merge entity @e[type=minecraft:villager,limit=1,sort=nearest] {CustomName:"Dekker"} | F8: ="/tag @e[type=minecraft:villager,name="""&B8&""",limit=1] add npc_"&LOWER(B8) -> /tag @e[type=minecraft:villager,name="Dekker",limit=1] add npc_dekker
A9: Moonglow | B9: Inoo | C9: =VLOOKUP(A9&"|"&B9&"|"&"LOOK",'NPC Dialogue'!$A:$F,6,FALSE) -> An old gypsy. | E9: ="/data merge entity @e[type=minecraft:villager,limit=1,sort=nearest] {CustomName:"""&B9&"""}" -> /data merge entity @e[type=minecraft:villager,limit=1,sort=nearest] {CustomName:"Inoo"} | F9: ="/tag @e[type=minecraft:villager,name="""&B9&""",limit=1] add npc_"&LOWER(B9) -> /tag @e[type=minecraft:villager,name="Inoo",limit=1] add npc_inoo
A10: Moonglow | B10: Mariah | C10: =VLOOKUP(A10&"|"&B10&"|"&"LOOK",'NPC Dialogue'!$A:$F,6,FALSE) -> A young mage | E10: ="/data merge entity @e[type=minecraft:villager,limit=1,sort=nearest] {CustomName:"""&B10&"""}" -> /data merge entity @e[type=minecraft:villager,limit=1,sort=nearest] {CustomName:"Mariah"} | F10: ="/tag @e[type=minecraft:villager,name="""&B10&""",limit=1] add npc_"&LOWER(B10) -> /tag @e[type=minecraft:villager,name="Mariah",limit=1] add npc_mariah
A11: Moonglow | B11: Patric the Humble Shepherd | C11: =VLOOKUP(A11&"|"&B11&"|"&"LOOK",'NPC Dialogue'!$A:$F,6,FALSE) -> A meek shepherd. | E11: ="/data merge entity @e[type=minecraft:villager,limit=1,sort=nearest] {CustomName:"""&B11&"""}" -> /data merge entity @e[type=minecraft:villager,limit=1,sort=nearest] {CustomName:"Patric the Humble Shepherd"} | F11: /tag @e[type=minecraft:villager,name="Patric the Humble Shepherd",limit=1] add npc_patric_the_humble_shepherd
A12: Moonglow | B12: Rebelias | C12: =VLOOKUP(A12&"|"&B12&"|"&"LOOK",'NPC Dialogue'!$A:$F,6,FALSE) -> A mystic wizard. | E12: ="/data merge entity @e[type=minecraft:villager,limit=1,sort=nearest] {CustomName:"""&B12&"""}" -> /data merge entity @e[type=minecraft:villager,limit=1,sort=nearest] {CustomName:"Rebelias"} | F12: ="/tag @e[type=minecraft:villager,name="""&B12&""",limit=1] add npc_"&LOWER(B12) -> /tag @e[type=minecraft:villager,name="Rebelias",limit=1] add npc_rebelias
A13: Moonglow | B13: Scatu | C13: =VLOOKUP(A13&"|"&B13&"|"&"LOOK",'NPC Dialogue'!$A:$F,6,FALSE) -> I am the Proprietor of Inn | E13: ="/data merge entity @e[type=minecraft:villager,limit=1,sort=nearest] {CustomName:"""&B13&"""}" -> /data merge entity @e[type=minecraft:villager,limit=1,sort=nearest] {CustomName:"Scatu"} | F13: ="/tag @e[type=minecraft:villager,name="""&B13&""",limit=1] add npc_"&LOWER(B13) -> /tag @e[type=minecraft:villager,name="Scatu",limit=1] add npc_scatu
A14: Moonglow | B14: Shakespeare | C14: =VLOOKUP(A14&"|"&B14&"|"&"LOOK",'NPC Dialogue'!$A:$F,6,FALSE) -> A wise wizard. | E14: ="/data merge entity @e[type=minecraft:villager,limit=1,sort=nearest] {CustomName:"""&B14&"""}" -> /data merge entity @e[type=minecraft:villager,limit=1,sort=nearest] {CustomName:"Shakespeare"} | F14: ="/tag @e[type=minecraft:villager,name="""&B14&""",limit=1] add npc_"&LOWER(B14) -> /tag @e[type=minecraft:villager,name="Shakespeare",limit=1] add npc_shakespeare
A15: Moonglow | B15: Shazom | C15: =VLOOKUP(A15&"|"&B15&"|"&"LOOK",'NPC Dialogue'!$A:$F,6,FALSE) -> A dying young wizard. | E15: ="/data merge entity @e[type=minecraft:villager,limit=1,sort=nearest] {CustomName:"""&B15&"""}" -> /data merge entity @e[type=minecraft:villager,limit=1,sort=nearest] {CustomName:"Shazom"} | F15: ="/tag @e[type=minecraft:villager,name="""&B15&""",limit=1] add npc_"&LOWER(B15) -> /tag @e[type=minecraft:villager,name="Shazom",limit=1] add npc_shazom
A16: Moonglow | B16: Tracie | C16: =VLOOKUP(A16&"|"&B16&"|"&"LOOK",'NPC Dialogue'!$A:$F,6,FALSE) -> Starving journalist | E16: ="/data merge entity @e[type=minecraft:villager,limit=1,sort=nearest] {CustomName:"""&B16&"""}" -> /data merge entity @e[type=minecraft:villager,limit=1,sort=nearest] {CustomName:"Tracie"} | F16: ="/tag @e[type=minecraft:villager,name="""&B16&""",limit=1] add npc_"&LOWER(B16) -> /tag @e[type=minecraft:villager,name="Tracie",limit=1] add npc_tracie
A17: Moonglow | B17: Tyrone | C17: =VLOOKUP(A17&"|"&B17&"|"&"LOOK",'NPC Dialogue'!$A:$F,6,FALSE) -> A battered mage. | E17: ="/data merge entity @e[type=minecraft:villager,limit=1,sort=nearest] {CustomName:"""&B17&"""}" -> /data merge entity @e[type=minecraft:villager,limit=1,sort=nearest] {CustomName:"Tyrone"} | F17: ="/tag @e[type=minecraft:villager,name="""&B17&""",limit=1] add npc_"&LOWER(B17) -> /tag @e[type=minecraft:villager,name="Tyrone",limit=1] add npc_tyrone
A18: Moonglow | B18: William | C18: =VLOOKUP(A18&"|"&B18&"|"&"LOOK",'NPC Dialogue'!$A:$F,6,FALSE) -> A Nitwit eating a sandwich. | E18: ="/data merge entity @e[type=minecraft:villager,limit=1,sort=nearest] {CustomName:"""&B18&"""}" -> /data merge entity @e[type=minecraft:villager,limit=1,sort=nearest] {CustomName:"William"} | F18: ="/tag @e[type=minecraft:villager,name="""&B18&""",limit=1] add npc_"&LOWER(B18) -> /tag @e[type=minecraft:villager,name="William",limit=1] add npc_william
A19: Moonglow | B19: Shaman | C19: =VLOOKUP(A19&"|"&B19&"|"&"LOOK",'NPC Dialogue'!$A:$F,6,FALSE) -> I am the Proprietor of Sage Deli, here. | E19: ="/data merge entity @e[type=minecraft:villager,limit=1,sort=nearest] {CustomName:"""&B19&"""}" -> /data merge entity @e[type=minecraft:villager,limit=1,sort=nearest] {CustomName:"Shaman"} | F19: ="/tag @e[type=minecraft:villager,name="""&B19&""",limit=1] add npc_"&LOWER(B19) -> /tag @e[type=minecraft:villager,name="Shaman",limit=1] add npc_shaman
A20: Moonglow | B20: Harmony | C20: =VLOOKUP(A20&"|"&B20&"|"&"LOOK",'NPC Dialogue'!$A:$F,6,FALSE) -> I am the Proprietor of The Healer shoppe. | E20: ="/data merge entity @e[type=minecraft:villager,limit=1,sort=nearest] {CustomName:"""&B20&"""}" -> /data merge entity @e[type=minecraft:villager,limit=1,sort=nearest] {CustomName:"Harmony"} | F20: ="/tag @e[type=minecraft:villager,name="""&B20&""",limit=1] add npc_"&LOWER(B20) -> /tag @e[type=minecraft:villager,name="Harmony",limit=1] add npc_harmony
A21: Moonglow | B21: Margot | C21: =IF(ISNA(VLOOKUP(A21&"|"&B21&"|"&"LOOK",'NPC Dialogue'!$A:$F,6,FALSE)),VLOOKUP(A21&"|"&B21&"|"&"You see...",'NPC Dialogue'!$A:$F,6,FALSE),VLOOKUP(A21&"|"&B21&"|"&"LOOK",'NPC Dialogue'!$A:$F,6,FALSE)) -> I am the Propriety of Magical Herbs | E21: ="/data merge entity @e[type=minecraft:villager,limit=1,sort=nearest] {CustomName:"""&B21&"""}" -> /data merge entity @e[type=minecraft:villager,limit=1,sort=nearest] {CustomName:"Margot"} | F21: ="/tag @e[type=minecraft:villager,name="""&B21&""",limit=1] add npc_"&LOWER(B21) -> /tag @e[type=minecraft:villager,name="Margot",limit=1] add npc_margot
A22: Trinsic | B22: Aristotle | C22: =IF(ISNA(VLOOKUP(A22&"|"&B22&"|"&"LOOK",'NPC Dialogue'!$A:$F,6,FALSE)),VLOOKUP(A22&"|"&B22&"|"&"You see..",'NPC Dialogue'!$A:$F,6,FALSE),VLOOKUP(A22&"|"&B22&"|"&"LOOK",'NPC Dialogue'!$A:$F,6,FALSE)) -> A dignified paladin. | D22: Cartographer | E22: ="/data merge entity @e[type=minecraft:villager,limit=1,sort=nearest] {CustomName:"""&B22&"""}" -> /data merge entity @e[type=minecraft:villager,limit=1,sort=nearest] {CustomName:"Aristotle"} | F22: ="/tag @e[type=minecraft:villager,name="""&B22&""",limit=1] add npc_"&LOWER(B22) -> /tag @e[type=minecraft:villager,name="Aristotle",limit=1] add npc_aristotle
A23: Trinsic | B23: Jean | C23: =IF(ISNA(VLOOKUP(A23&"|"&B23&"|"&"LOOK",'NPC Dialogue'!$A:$F,6,FALSE)),VLOOKUP(A23&"|"&B23&"|"&"You see..",'NPC Dialogue'!$A:$F,6,FALSE),VLOOKUP(A23&"|"&B23&"|"&"LOOK",'NPC Dialogue'!$A:$F,6,FALSE)) -> I am the Proprietor of Duelling Weapons, here. | D23: Weaponsmith | E23: ="/data merge entity @e[type=minecraft:villager,limit=1,sort=nearest] {CustomName:"""&B23&"""}" -> /data merge entity @e[type=minecraft:villager,limit=1,sort=nearest] {CustomName:"Jean"} | F23: ="/tag @e[type=minecraft:villager,name="""&B23&""",limit=1] add npc_"&LOWER(B23) -> /tag @e[type=minecraft:villager,name="Jean",limit=1] add npc_jean
A24: Trinsic | B24: Jumar | C24: =IF(ISNA(VLOOKUP(A24&"|"&B24&"|"&"LOOK",'NPC Dialogue'!$A:$F,6,FALSE)),VLOOKUP(A24&"|"&B24&"|"&"You see..",'NPC Dialogue'!$A:$F,6,FALSE),VLOOKUP(A24&"|"&B24&"|"&"LOOK",'NPC Dialogue'!$A:$F,6,FALSE)) -> I am the Proprietor of Duelling Armour, here. | D24: Armorer | E24: ="/data merge entity @e[type=minecraft:villager,limit=1,sort=nearest] {CustomName:"""&B24&"""}" -> /data merge entity @e[type=minecraft:villager,limit=1,sort=nearest] {CustomName:"Jumar"} | F24: ="/tag @e[type=minecraft:villager,name="""&B24&""",limit=1] add npc_"&LOWER(B24) -> /tag @e[type=minecraft:villager,name="Jumar",limit=1] add npc_jumar
A25: Trinsic | B25: Kline | C25: =IF(ISNA(VLOOKUP(A25&"|"&B25&"|"&"LOOK",'NPC Dialogue'!$A:$F,6,FALSE)),VLOOKUP(A25&"|"&B25&"|"&"You see..",'NPC Dialogue'!$A:$F,6,FALSE),VLOOKUP(A25&"|"&B25&"|"&"LOOK",'NPC Dialogue'!$A:$F,6,FALSE)) -> A searching paladin! | D25: Librarian | E25: ="/data merge entity @e[type=minecraft:villager,limit=1,sort=nearest] {CustomName:"""&B25&"""}" -> /data merge entity @e[type=minecraft:villager,limit=1,sort=nearest] {CustomName:"Kline"} | F25: ="/tag @e[type=minecraft:villager,name="""&B25&""",limit=1] add npc_"&LOWER(B25) -> /tag @e[type=minecraft:villager,name="Kline",limit=1] add npc_kline
A26: Trinsic | B26: Lexington | C26: =IF(ISNA(VLOOKUP(A26&"|"&B26&"|"&"LOOK",'NPC Dialogue'!$A:$F,6,FALSE)),VLOOKUP(A26&"|"&B26&"|"&"You see..",'NPC Dialogue'!$A:$F,6,FALSE),VLOOKUP(A26&"|"&B26&"|"&"LOOK",'NPC Dialogue'!$A:$F,6,FALSE)) -> A shining paladin. | D26: Armorer | E26: ="/data merge entity @e[type=minecraft:villager,limit=1,sort=nearest] {CustomName:"""&B26&"""}" -> /data merge entity @e[type=minecraft:villager,limit=1,sort=nearest] {CustomName:"Lexington"} | F26: ="/tag @e[type=minecraft:villager,name="""&B26&""",limit=1] add npc_"&LOWER(B26) -> /tag @e[type=minecraft:villager,name="Lexington",limit=1] add npc_lexington
A27: Trinsic | B27: Rigmore | C27: =IF(ISNA(VLOOKUP(A27&"|"&B27&"|"&"LOOK",'NPC Dialogue'!$A:$F,6,FALSE)),VLOOKUP(A27&"|"&B27&"|"&"You see..",'NPC Dialogue'!$A:$F,6,FALSE),VLOOKUP(A27&"|"&B27&"|"&"LOOK",'NPC Dialogue'!$A:$F,6,FALSE)) -> A strong paladin. | D27: Armorer | E27: ="/data merge entity @e[type=minecraft:villager,limit=1,sort=nearest] {CustomName:"""&B27&"""}" -> /data merge entity @e[type=minecraft:villager,limit=1,sort=nearest] {CustomName:"Rigmore"} | F27: ="/tag @e[type=minecraft:villager,name="""&B27&""",limit=1] add npc_"&LOWER(B27) -> /tag @e[type=minecraft:villager,name="Rigmore",limit=1] add npc_rigmore
A28: Trinsic | B28: Swindrik | C28: =IF(ISNA(VLOOKUP(A28&"|"&B28&"|"&"LOOK",'NPC Dialogue'!$A:$F,6,FALSE)),VLOOKUP(A28&"|"&B28&"|"&"You see..",'NPC Dialogue'!$A:$F,6,FALSE),VLOOKUP(A28&"|"&B28&"|"&"LOOK",'NPC Dialogue'!$A:$F,6,FALSE)) -> A tall wizard. | D28: Cleric | E28: ="/data merge entity @e[type=minecraft:villager,limit=1,sort=nearest] {CustomName:"""&B28&"""}" -> /data merge entity @e[type=minecraft:villager,limit=1,sort=nearest] {CustomName:"Swindrik"} | F28: ="/tag @e[type=minecraft:villager,name="""&B28&""",limit=1] add npc_"&LOWER(B28) -> /tag @e[type=minecraft:villager,name="Swindrik",limit=1] add npc_swindrik
A29: Trinsic | B29: Terran | C29: =IF(ISNA(VLOOKUP(A29&"|"&B29&"|"&"LOOK",'NPC Dialogue'!$A:$F,6,FALSE)),VLOOKUP(A29&"|"&B29&"|"&"You see..",'NPC Dialogue'!$A:$F,6,FALSE),VLOOKUP(A29&"|"&B29&"|"&"LOOK",'NPC Dialogue'!$A:$F,6,FALSE)) -> I am the Proprietor of The Keg Tap, here. | D29: Butcher | E29: ="/data merge entity @e[type=minecraft:villager,limit=1,sort=nearest] {CustomName:"""&B29&"""}" -> /data merge entity @e[type=minecraft:villager,limit=1,sort=nearest] {CustomName:"Terran"} | F29: ="/tag @e[type=minecraft:villager,name="""&B29&""",limit=1] add npc_"&LOWER(B29) -> /tag @e[type=minecraft:villager,name="Terran",limit=1] add npc_terran
A30: Trinsic | B30: Terrin | C30: =IF(ISNA(VLOOKUP(A30&"|"&B30&"|"&"LOOK",'NPC Dialogue'!$A:$F,6,FALSE)),VLOOKUP(A30&"|"&B30&"|"&"You see..",'NPC Dialogue'!$A:$F,6,FALSE),VLOOKUP(A30&"|"&B30&"|"&"LOOK",'NPC Dialogue'!$A:$F,6,FALSE)) -> A scared, cowering nitwit | D30: Nitwit | E30: ="/data merge entity @e[type=minecraft:villager,limit=1,sort=nearest] {CustomName:"""&B30&"""}" -> /data merge entity @e[type=minecraft:villager,limit=1,sort=nearest] {CustomName:"Terrin"} | F30: ="/tag @e[type=minecraft:villager,name="""&B30&""",limit=1] add npc_"&LOWER(B30) -> /tag @e[type=minecraft:villager,name="Terrin",limit=1] add npc_terrin
A31: Trinsic | B31: Winthrop | C31: =IF(ISNA(VLOOKUP(A31&"|"&B31&"|"&"LOOK",'NPC Dialogue'!$A:$F,6,FALSE)),VLOOKUP(A31&"|"&B31&"|"&"You see..",'NPC Dialogue'!$A:$F,6,FALSE),VLOOKUP(A31&"|"&B31&"|"&"LOOK",'NPC Dialogue'!$A:$F,6,FALSE)) -> A scruffy merchant. | D31: Fisherman | E31: ="/data merge entity @e[type=minecraft:villager,limit=1,sort=nearest] {CustomName:"""&B31&"""}" -> /data merge entity @e[type=minecraft:villager,limit=1,sort=nearest] {CustomName:"Winthrop"} | F31: ="/tag @e[type=minecraft:villager,name="""&B31&""",limit=1] add npc_"&LOWER(B31) -> /tag @e[type=minecraft:villager,name="Winthrop",limit=1] add npc_winthrop
A32: Trinsic | B32: Zajac | C32: =IF(ISNA(VLOOKUP(A32&"|"&B32&"|"&"LOOK",'NPC Dialogue'!$A:$F,6,FALSE)),VLOOKUP(A32&"|"&B32&"|"&"You see..",'NPC Dialogue'!$A:$F,6,FALSE),VLOOKUP(A32&"|"&B32&"|"&"LOOK",'NPC Dialogue'!$A:$F,6,FALSE)) -> I am the Proprietor of the Honorable Inn, here. | D32: Shepherd | E32: ="/data merge entity @e[type=minecraft:villager,limit=1,sort=nearest] {CustomName:"""&B32&"""}" -> /data merge entity @e[type=minecraft:villager,limit=1,sort=nearest] {CustomName:"Zajac"} | F32: ="/tag @e[type=minecraft:villager,name="""&B32&""",limit=1] add npc_"&LOWER(B32) -> /tag @e[type=minecraft:villager,name="Zajac",limit=1] add npc_zajac
A33: Yew | B33: Beggar | C33: =IF(ISNA(VLOOKUP(A33&"|"&B33&"|"&"LOOK",'NPC Dialogue'!$A:$F,6,FALSE)),VLOOKUP(A33&"|"&B33&"|"&"You see..",'NPC Dialogue'!$A:$F,6,FALSE),VLOOKUP(A33&"|"&B33&"|"&"LOOK",'NPC Dialogue'!$A:$F,6,FALSE)) -> A poor beggar. | D33: Nitwit | E33: ="/data merge entity @e[type=minecraft:villager,limit=1,sort=nearest] {CustomName:"""&B33&"""}" -> /data merge entity @e[type=minecraft:villager,limit=1,sort=nearest] {CustomName:"Beggar"} | F33: ="/tag @e[type=minecraft:villager,name="""&B33&""",limit=1] add npc_"&SUBSTITUTE(LOWER(B33)," ","_") -> /tag @e[type=minecraft:villager,name="Beggar",limit=1] add npc_beggar | G33: =B33 -> Beggar | H33: =MID(F33,I33+4,99) -> npc_beggar | I33: =FIND("add npc",F33) -> 56
A34: Yew | B34: Calumny | C34: =IF(ISNA(VLOOKUP(A34&"|"&B34&"|"&"LOOK",'NPC Dialogue'!$A:$F,6,FALSE)),VLOOKUP(A34&"|"&B34&"|"&"You see..",'NPC Dialogue'!$A:$F,6,FALSE),VLOOKUP(A34&"|"&B34&"|"&"LOOK",'NPC Dialogue'!$A:$F,6,FALSE)) -> A solemn druid. | D34: Librarian - inside eastern tree | E34: ="/data merge entity @e[type=minecraft:villager,limit=1,sort=nearest] {CustomName:"""&B34&"""}" -> /data merge entity @e[type=minecraft:villager,limit=1,sort=nearest] {CustomName:"Calumny"} | F34: ="/tag @e[type=minecraft:villager,name="""&B34&""",limit=1] add npc_"&SUBSTITUTE(LOWER(B34)," ","_") -> /tag @e[type=minecraft:villager,name="Calumny",limit=1] add npc_calumny | G34: =B34 -> Calumny | H34: =MID(F34,I34+4,99) -> npc_calumny | I34: =FIND("add npc",F34) -> 57
A35: Yew | B35: Court Guard | C35: =IF(ISNA(VLOOKUP(A35&"|"&B35&"|"&"LOOK",'NPC Dialogue'!$A:$F,6,FALSE)),VLOOKUP(A35&"|"&B35&"|"&"You see..",'NPC Dialogue'!$A:$F,6,FALSE),VLOOKUP(A35&"|"&B35&"|"&"LOOK",'NPC Dialogue'!$A:$F,6,FALSE)) -> A tall guard | D35: Leathermaker | E35: ="/data merge entity @e[type=minecraft:villager,limit=1,sort=nearest] {CustomName:"""&B35&"""}" -> /data merge entity @e[type=minecraft:villager,limit=1,sort=nearest] {CustomName:"Court Guard"} | F35: ="/tag @e[type=minecraft:villager,name="""&B35&""",limit=1] add npc_"&SUBSTITUTE(LOWER(B35)," ","_") -> /tag @e[type=minecraft:villager,name="Court Guard",limit=1] add npc_court_guard | G35: =B35 -> Court Guard | H35: =MID(F35,I35+4,99) -> npc_court_guard | I35: =FIND("add npc",F35) -> 61
A36: Yew | B36: A.Druid | C36: =IF(ISNA(VLOOKUP(A36&"|"&B36&"|"&"LOOK",'NPC Dialogue'!$A:$F,6,FALSE)),VLOOKUP(A36&"|"&B36&"|"&"You see..",'NPC Dialogue'!$A:$F,6,FALSE),VLOOKUP(A36&"|"&B36&"|"&"LOOK",'NPC Dialogue'!$A:$F,6,FALSE)) -> #N/A | D36: Librarian - wandering around the grounds | E36: ="/data merge entity @e[type=minecraft:villager,limit=1,sort=nearest] {CustomName:"""&B36&"""}" -> /data merge entity @e[type=minecraft:villager,limit=1,sort=nearest] {CustomName:"A.Druid"} | F36: ="/tag @e[type=minecraft:villager,name="""&B36&""",limit=1] add npc_"&SUBSTITUTE(LOWER(B36)," ","_") -> /tag @e[type=minecraft:villager,name="A.Druid",limit=1] add npc_a.druid | G36: =B36 -> A.Druid | H36: =MID(F36,I36+4,99) -> npc_a.druid | I36: =FIND("add npc",F36) -> 57
A37: Yew | B37: DWP | C37: =IF(ISNA(VLOOKUP(A37&"|"&B37&"|"&"LOOK",'NPC Dialogue'!$A:$F,6,FALSE)),VLOOKUP(A37&"|"&B37&"|"&"You see..",'NPC Dialogue'!$A:$F,6,FALSE),VLOOKUP(A37&"|"&B37&"|"&"LOOK",'NPC Dialogue'!$A:$F,6,FALSE)) -> A wise druid. | D37: Librarian - Welcomer | E37: ="/data merge entity @e[type=minecraft:villager,limit=1,sort=nearest] {CustomName:"""&B37&"""}" -> /data merge entity @e[type=minecraft:villager,limit=1,sort=nearest] {CustomName:"DWP"} | F37: ="/tag @e[type=minecraft:villager,name="""&B37&""",limit=1] add npc_"&SUBSTITUTE(LOWER(B37)," ","_") -> /tag @e[type=minecraft:villager,name="DWP",limit=1] add npc_dwp | G37: =B37 -> DWP | H37: =MID(F37,I37+4,99) -> npc_dwp | I37: =FIND("add npc",F37) -> 53
A38: Yew | B38: Frida | C38: =IF(ISNA(VLOOKUP(A38&"|"&B38&"|"&"LOOK",'NPC Dialogue'!$A:$F,6,FALSE)),VLOOKUP(A38&"|"&B38&"|"&"You see..",'NPC Dialogue'!$A:$F,6,FALSE),VLOOKUP(A38&"|"&B38&"|"&"LOOK",'NPC Dialogue'!$A:$F,6,FALSE)) -> A withered form. | D38: Nitwit - in Healer | E38: ="/data merge entity @e[type=minecraft:villager,limit=1,sort=nearest] {CustomName:"""&B38&"""}" -> /data merge entity @e[type=minecraft:villager,limit=1,sort=nearest] {CustomName:"Frida"} | F38: ="/tag @e[type=minecraft:villager,name="""&B38&""",limit=1] add npc_"&SUBSTITUTE(LOWER(B38)," ","_") -> /tag @e[type=minecraft:villager,name="Frida",limit=1] add npc_frida | G38: =B38 -> Frida | H38: =MID(F38,I38+4,99) -> npc_frida | I38: =FIND("add npc",F38) -> 55
A39: Yew | B39: Guard | C39: =IF(ISNA(VLOOKUP(A39&"|"&B39&"|"&"LOOK",'NPC Dialogue'!$A:$F,6,FALSE)),VLOOKUP(A39&"|"&B39&"|"&"You see..",'NPC Dialogue'!$A:$F,6,FALSE),VLOOKUP(A39&"|"&B39&"|"&"LOOK",'NPC Dialogue'!$A:$F,6,FALSE)) -> A big guard | D39: Leathermaker - near Welcomer | E39: ="/data merge entity @e[type=minecraft:villager,limit=1,sort=nearest] {CustomName:"""&B39&"""}" -> /data merge entity @e[type=minecraft:villager,limit=1,sort=nearest] {CustomName:"Guard"} | F39: ="/tag @e[type=minecraft:villager,name="""&B39&""",limit=1] add npc_"&SUBSTITUTE(LOWER(B39)," ","_") -> /tag @e[type=minecraft:villager,name="Guard",limit=1] add npc_guard | G39: =B39 -> Guard | H39: =MID(F39,I39+4,99) -> npc_guard | I39: =FIND("add npc",F39) -> 55
A40: Yew | B40: Jaana | C40: =IF(ISNA(VLOOKUP(A40&"|"&B40&"|"&"LOOK",'NPC Dialogue'!$A:$F,6,FALSE)),VLOOKUP(A40&"|"&B40&"|"&"You see..",'NPC Dialogue'!$A:$F,6,FALSE),VLOOKUP(A40&"|"&B40&"|"&"LOOK",'NPC Dialogue'!$A:$F,6,FALSE)) -> A quiet druid | D40: Shepherd - north side of Fire | E40: ="/data merge entity @e[type=minecraft:villager,limit=1,sort=nearest] {CustomName:"""&B40&"""}" -> /data merge entity @e[type=minecraft:villager,limit=1,sort=nearest] {CustomName:"Jaana"} | F40: ="/tag @e[type=minecraft:villager,name="""&B40&""",limit=1] add npc_"&SUBSTITUTE(LOWER(B40)," ","_") -> /tag @e[type=minecraft:villager,name="Jaana",limit=1] add npc_jaana | G40: =B40 -> Jaana | H40: =MID(F40,I40+4,99) -> npc_jaana | I40: =FIND("add npc",F40) -> 55
A41: Yew | B41: Jail Guard | C41: =IF(ISNA(VLOOKUP(A41&"|"&B41&"|"&"LOOK",'NPC Dialogue'!$A:$F,6,FALSE)),VLOOKUP(A41&"|"&B41&"|"&"You see..",'NPC Dialogue'!$A:$F,6,FALSE),VLOOKUP(A41&"|"&B41&"|"&"LOOK",'NPC Dialogue'!$A:$F,6,FALSE)) -> A big guard. | D41: Leathermaker | E41: ="/data merge entity @e[type=minecraft:villager,limit=1,sort=nearest] {CustomName:"""&B41&"""}" -> /data merge entity @e[type=minecraft:villager,limit=1,sort=nearest] {CustomName:"Jail Guard"} | F41: ="/tag @e[type=minecraft:villager,name="""&B41&""",limit=1] add npc_"&SUBSTITUTE(LOWER(B41)," ","_") -> /tag @e[type=minecraft:villager,name="Jail Guard",limit=1] add npc_jail_guard | G41: =B41 -> Jail Guard | H41: =MID(F41,I41+4,99) -> npc_jail_guard | I41: =FIND("add npc",F41) -> 60
A42: Yew | B42: Pinrod | C42: =IF(ISNA(VLOOKUP(A42&"|"&B42&"|"&"LOOK",'NPC Dialogue'!$A:$F,6,FALSE)),VLOOKUP(A42&"|"&B42&"|"&"You see..",'NPC Dialogue'!$A:$F,6,FALSE),VLOOKUP(A42&"|"&B42&"|"&"LOOK",'NPC Dialogue'!$A:$F,6,FALSE)) -> A thin man. | D42: Fletcher - a courtier near Talfourd | E42: ="/data merge entity @e[type=minecraft:villager,limit=1,sort=nearest] {CustomName:"""&B42&"""}" -> /data merge entity @e[type=minecraft:villager,limit=1,sort=nearest] {CustomName:"Pinrod"} | F42: ="/tag @e[type=minecraft:villager,name="""&B42&""",limit=1] add npc_"&SUBSTITUTE(LOWER(B42)," ","_") -> /tag @e[type=minecraft:villager,name="Pinrod",limit=1] add npc_pinrod | G42: =B42 -> Pinrod | H42: =MID(F42,I42+4,99) -> npc_pinrod | I42: =FIND("add npc",F42) -> 56
A43: Yew | B43: Ranger Rick | C43: =IF(ISNA(VLOOKUP(A43&"|"&B43&"|"&"LOOK",'NPC Dialogue'!$A:$F,6,FALSE)),VLOOKUP(A43&"|"&B43&"|"&"You see..",'NPC Dialogue'!$A:$F,6,FALSE),VLOOKUP(A43&"|"&B43&"|"&"LOOK",'NPC Dialogue'!$A:$F,6,FALSE)) -> A sleek ranger. | D43: Cartographer - at DryGoods | E43: ="/data merge entity @e[type=minecraft:villager,limit=1,sort=nearest] {CustomName:"""&B43&"""}" -> /data merge entity @e[type=minecraft:villager,limit=1,sort=nearest] {CustomName:"Ranger Rick"} | F43: ="/tag @e[type=minecraft:villager,name="""&B43&""",limit=1] add npc_"&SUBSTITUTE(LOWER(B43)," ","_") -> /tag @e[type=minecraft:villager,name="Ranger Rick",limit=1] add npc_ranger_rick | G43: =B43 -> Ranger Rick | H43: =MID(F43,I43+4,99) -> npc_ranger_rick | I43: =FIND("add npc",F43) -> 61
A44: Yew | B44: Short Round | C44: =IF(ISNA(VLOOKUP(A44&"|"&B44&"|"&"LOOK",'NPC Dialogue'!$A:$F,6,FALSE)),VLOOKUP(A44&"|"&B44&"|"&"You see..",'NPC Dialogue'!$A:$F,6,FALSE),VLOOKUP(A44&"|"&B44&"|"&"LOOK",'NPC Dialogue'!$A:$F,6,FALSE)) -> A small child | D44: Nitwit - outside east side of Dry Goods | E44: ="/data merge entity @e[type=minecraft:villager,limit=1,sort=nearest] {CustomName:"""&B44&"""}" -> /data merge entity @e[type=minecraft:villager,limit=1,sort=nearest] {CustomName:"Short Round"} | F44: ="/tag @e[type=minecraft:villager,name="""&B44&""",limit=1] add npc_"&SUBSTITUTE(LOWER(B44)," ","_") -> /tag @e[type=minecraft:villager,name="Short Round",limit=1] add npc_short_round | G44: =B44 -> Short Round | H44: =MID(F44,I44+4,99) -> npc_short_round | I44: =FIND("add npc",F44) -> 61
... A47: Yew | B47: Vorpal | C47: =IF(ISNA(VLOOKUP(A47&"|"&B47&"|"&"LOOK",'NPC Dialogue'!$A:$F,6,FALSE)),VLOOKUP(A47&"|"&B47&"|"&"You see..",'NPC Dialogue'!$A:$F,6,FALSE),VLOOKUP(A47&"|"&B47&"|"&"LOOK",'NPC Dialogue'!$A:$F,6,FALSE)) -> A mean nasty ugly villain! | D47: Weaponsmith | E47: ="/data merge entity @e[type=minecraft:villager,limit=1,sort=nearest] {CustomName:"""&B47&"""}" -> /data merge entity @e[type=minecraft:villager,limit=1,sort=nearest] {CustomName:"Vorpal"} | F47: ="/tag @e[type=minecraft:villager,name="""&B47&""",limit=1] add npc_"&SUBSTITUTE(LOWER(B47)," ","_") -> /tag @e[type=minecraft:villager,name="Vorpal",limit=1] add npc_vorpal | G47: =B47 -> Vorpal | H47: =MID(F47,I47+4,99) -> npc_vorpal | I47: =FIND("add npc",F47) -> 56
A48: Yew | B48: Donnar | C48: Proprietor of The Dry Goods | D48: Fletcher | E48: ="/data merge entity @e[type=minecraft:villager,limit=1,sort=nearest] {CustomName:"""&B48&"""}" -> /data merge entity @e[type=minecraft:villager,limit=1,sort=nearest] {CustomName:"Donnar"} | F48: ="/tag @e[type=minecraft:villager,name="""&B48&""",limit=1] add npc_"&SUBSTITUTE(LOWER(B48)," ","_") -> /tag @e[type=minecraft:villager,name="Donnar",limit=1] add npc_donnar | G48: =B48 -> Donnar | H48: =MID(F48,I48+4,99) -> npc_donnar | I48: =FIND("add npc",F48) -> 56
A49: Yew | B49: Justin | C49: Proprietor of Just Healing | E49: ="/data merge entity @e[type=minecraft:villager,limit=1,sort=nearest] {CustomName:"""&B49&"""}" -> /data merge entity @e[type=minecraft:villager,limit=1,sort=nearest] {CustomName:"Justin"} | F49: ="/tag @e[type=minecraft:villager,name="""&B49&""",limit=1] add npc_"&SUBSTITUTE(LOWER(B49)," ","_") -> /tag @e[type=minecraft:villager,name="Justin",limit=1] add npc_justin | G49: =B49 -> Justin | H49: =MID(F49,I49+4,99) -> npc_justin | I49: =FIND("add npc",F49) -> 56
A50: Jhelom | B50: Aesop | C50: =IF(ISNA(VLOOKUP(A50&"|"&B50&"|"&"LOOK",'NPC Dialogue'!$A:$F,6,FALSE)),VLOOKUP(A50&"|"&B50&"|"&"You see..",'NPC Dialogue'!$A:$F,6,FALSE),VLOOKUP(A50&"|"&B50&"|"&"LOOK",'NPC Dialogue'!$A:$F,6,FALSE)) -> A small man. | D50: Fletcher | E50: ="/data merge entity @e[type=minecraft:villager,limit=1,sort=nearest] {CustomName:"""&B50&"""}" -> /data merge entity @e[type=minecraft:villager,limit=1,sort=nearest] {CustomName:"Aesop"} | F50: ="/tag @e[type=minecraft:villager,name="""&B50&""",limit=1] add npc_"&SUBSTITUTE(LOWER(B50)," ","_") -> /tag @e[type=minecraft:villager,name="Aesop",limit=1] add npc_aesop | G50: =B50 -> Aesop | H50: =MID(F50,I50+4,99) -> npc_aesop | I50: =FIND("add npc",F50) -> 55
A51: Jhelom | B51: Gate Guard | C51: =IF(ISNA(VLOOKUP(A51&"|"&B51&"|"&"LOOK",'NPC Dialogue'!$A:$F,6,FALSE)),VLOOKUP(A51&"|"&B51&"|"&"You see..",'NPC Dialogue'!$A:$F,6,FALSE),VLOOKUP(A51&"|"&B51&"|"&"LOOK",'NPC Dialogue'!$A:$F,6,FALSE)) -> A stern guard. | D51: Weaponsmith | E51: ="/data merge entity @e[type=minecraft:villager,limit=1,sort=nearest] {CustomName:"""&B51&"""}" -> /data merge entity @e[type=minecraft:villager,limit=1,sort=nearest] {CustomName:"Gate Guard"} | F51: ="/tag @e[type=minecraft:villager,name="""&B51&""",limit=1] add npc_"&SUBSTITUTE(LOWER(B51)," ","_") -> /tag @e[type=minecraft:villager,name="Gate Guard",limit=1] add npc_gate_guard | G51: =B51 -> Gate Guard | H51: =MID(F51,I51+4,99) -> npc_gate_guard | I51: =FIND("add npc",F51) -> 60
A52: Jhelom | B52: Luke | C52: =IF(ISNA(VLOOKUP(A52&"|"&B52&"|"&"LOOK",'NPC Dialogue'!$A:$F,6,FALSE)),VLOOKUP(A52&"|"&B52&"|"&"You see..",'NPC Dialogue'!$A:$F,6,FALSE),VLOOKUP(A52&"|"&B52&"|"&"LOOK",'NPC Dialogue'!$A:$F,6,FALSE)) -> A ranger with a far away look. | D52: At the Inn; a cartographer | E52: ="/data merge entity @e[type=minecraft:villager,limit=1,sort=nearest] {CustomName:"""&B52&"""}" -> /data merge entity @e[type=minecraft:villager,limit=1,sort=nearest] {CustomName:"Luke"} | F52: ="/tag @e[type=minecraft:villager,name="""&B52&""",limit=1] add npc_"&SUBSTITUTE(LOWER(B52)," ","_") -> /tag @e[type=minecraft:villager,name="Luke",limit=1] add npc_luke | G52: =B52 -> Luke | H52: =MID(F52,I52+4,99) -> npc_luke | I52: =FIND("add npc",F52) -> 54
A53: Jhelom | B53: Max | C53: =IF(ISNA(VLOOKUP(A53&"|"&B53&"|"&"LOOK",'NPC Dialogue'!$A:$F,6,FALSE)),VLOOKUP(A53&"|"&B53&"|"&"You see..",'NPC Dialogue'!$A:$F,6,FALSE),VLOOKUP(A53&"|"&B53&"|"&"LOOK",'NPC Dialogue'!$A:$F,6,FALSE)) -> The housekeeper. | D53: Shepherd | E53: ="/data merge entity @e[type=minecraft:villager,limit=1,sort=nearest] {CustomName:"""&B53&"""}" -> /data merge entity @e[type=minecraft:villager,limit=1,sort=nearest] {CustomName:"Max"} | F53: ="/tag @e[type=minecraft:villager,name="""&B53&""",limit=1] add npc_"&SUBSTITUTE(LOWER(B53)," ","_") -> /tag @e[type=minecraft:villager,name="Max",limit=1] add npc_max | G53: =B53 -> Max | H53: =MID(F53,I53+4,99) -> npc_max | I53: =FIND("add npc",F53) -> 53
A54: Jhelom | B54: Nostro | C54: =IF(ISNA(VLOOKUP(A54&"|"&B54&"|"&"LOOK",'NPC Dialogue'!$A:$F,6,FALSE)),VLOOKUP(A54&"|"&B54&"|"&"You see..",'NPC Dialogue'!$A:$F,6,FALSE),VLOOKUP(A54&"|"&B54&"|"&"LOOK",'NPC Dialogue'!$A:$F,6,FALSE)) -> A withering soul | D54: In the corner nearest healing shop | E54: ="/data merge entity @e[type=minecraft:villager,limit=1,sort=nearest] {CustomName:"""&B54&"""}" -> /data merge entity @e[type=minecraft:villager,limit=1,sort=nearest] {CustomName:"Nostro"} | F54: ="/tag @e[type=minecraft:villager,name="""&B54&""",limit=1] add npc_"&SUBSTITUTE(LOWER(B54)," ","_") -> /tag @e[type=minecraft:villager,name="Nostro",limit=1] add npc_nostro | G54: =B54 -> Nostro | H54: =MID(F54,I54+4,99) -> npc_nostro | I54: =FIND("add npc",F54) -> 56
A55: Jhelom | B55: Senora | C55: =IF(ISNA(VLOOKUP(A55&"|"&B55&"|"&"LOOK",'NPC Dialogue'!$A:$F,6,FALSE)),VLOOKUP(A55&"|"&B55&"|"&"You see..",'NPC Dialogue'!$A:$F,6,FALSE),VLOOKUP(A55&"|"&B55&"|"&"LOOK",'NPC Dialogue'!$A:$F,6,FALSE)) -> A beautiful mage | D55: A cleric; in corner of castle nearest Avatar's room (near Hero). | E55: ="/data merge entity @e[type=minecraft:villager,limit=1,sort=nearest] {CustomName:"""&B55&"""}" -> /data merge entity @e[type=minecraft:villager,limit=1,sort=nearest] {CustomName:"Senora"} | F55: ="/tag @e[type=minecraft:villager,name="""&B55&""",limit=1] add npc_"&SUBSTITUTE(LOWER(B55)," ","_") -> /tag @e[type=minecraft:villager,name="Senora",limit=1] add npc_senora | G55: =B55 -> Senora | H55: =MID(F55,I55+4,99) -> npc_senora | I55: =FIND("add npc",F55) -> 56
A56: Jhelom | B56: Sir William | C56: =IF(ISNA(VLOOKUP(A56&"|"&B56&"|"&"LOOK",'NPC Dialogue'!$A:$F,6,FALSE)),VLOOKUP(A56&"|"&B56&"|"&"You see..",'NPC Dialogue'!$A:$F,6,FALSE),VLOOKUP(A56&"|"&B56&"|"&"LOOK",'NPC Dialogue'!$A:$F,6,FALSE)) -> A noble fighter. | D56: In the weapon shop; a Fletcher | E56: ="/data merge entity @e[type=minecraft:villager,limit=1,sort=nearest] {CustomName:"""&B56&"""}" -> /data merge entity @e[type=minecraft:villager,limit=1,sort=nearest] {CustomName:"Sir William"} | F56: ="/tag @e[type=minecraft:villager,name="""&B56&""",limit=1] add npc_"&SUBSTITUTE(LOWER(B56)," ","_") -> /tag @e[type=minecraft:villager,name="Sir William",limit=1] add npc_sir_william | G56: =B56 -> Sir William | H56: =MID(F56,I56+4,99) -> npc_sir_william | I56: =FIND("add npc",F56) -> 61
A57: Jhelom | B57: X | C57: =IF(ISNA(VLOOKUP(A57&"|"&B57&"|"&"LOOK",'NPC Dialogue'!$A:$F,6,FALSE)),VLOOKUP(A57&"|"&B57&"|"&"You see..",'NPC Dialogue'!$A:$F,6,FALSE),VLOOKUP(A57&"|"&B57&"|"&"LOOK",'NPC Dialogue'!$A:$F,6,FALSE)) -> A strange person | D57: outside heal shop; cartographer | E57: ="/data merge entity @e[type=minecraft:villager,limit=1,sort=nearest] {CustomName:"""&B57&"""}" -> /data merge entity @e[type=minecraft:villager,limit=1,sort=nearest] {CustomName:"X"} | F57: ="/tag @e[type=minecraft:villager,name="""&B57&""",limit=1] add npc_"&SUBSTITUTE(LOWER(B57)," ","_") -> /tag @e[type=minecraft:villager,name="X",limit=1] add npc_x | G57: =B57 -> X | H57: =MID(F57,I57+4,99) -> npc_x | I57: =FIND("add npc",F57) -> 51
A58: Jhelom | B58: Swen | C58: Nitwit in Bar | E58: ="/data merge entity @e[type=minecraft:villager,limit=1,sort=nearest] {CustomName:"""&B58&"""}" -> /data merge entity @e[type=minecraft:villager,limit=1,sort=nearest] {CustomName:"Swen"} | F58: ="/tag @e[type=minecraft:villager,name="""&B58&""",limit=1] add npc_"&SUBSTITUTE(LOWER(B58)," ","_") -> /tag @e[type=minecraft:villager,name="Swen",limit=1] add npc_swen | G58: =B58 -> Swen | H58: =MID(F58,I58+4,99) -> npc_swen | I58: =FIND("add npc",F58) -> 54
A59: Jhelom | B59: Hero | C59: In Hero's Lounge | E59: ="/data merge entity @e[type=minecraft:villager,limit=1,sort=nearest] {CustomName:"""&B59&"""}" -> /data merge entity @e[type=minecraft:villager,limit=1,sort=nearest] {CustomName:"Hero"} | F59: ="/tag @e[type=minecraft:villager,name="""&B59&""",limit=1] add npc_"&SUBSTITUTE(LOWER(B59)," ","_") -> /tag @e[type=minecraft:villager,name="Hero",limit=1] add npc_hero | G59: =B59 -> Hero | H59: =MID(F59,I59+4,99) -> npc_hero | I59: =FIND("add npc",F59) -> 54
A60: Jhelom | B60: Smith | C60: Horse | E60: ="/data merge entity @e[type=minecraft:villager,limit=1,sort=nearest] {CustomName:"""&B60&"""}" -> /data merge entity @e[type=minecraft:villager,limit=1,sort=nearest] {CustomName:"Smith"} | F60: ="/tag @e[type=minecraft:villager,name="""&B60&""",limit=1] add npc_"&SUBSTITUTE(LOWER(B60)," ","_") -> /tag @e[type=minecraft:villager,name="Smith",limit=1] add npc_smith | G60: =B60 -> Smith | H60: =MID(F60,I60+4,99) -> npc_smith | I60: =FIND("add npc",F60) -> 55
A61: Jhelom | B61: Celestial | C61: Celestial: tavern keeper of The Bloody Pub | E61: ="/data merge entity @e[type=minecraft:villager,limit=1,sort=nearest] {CustomName:"""&B61&"""}" -> /data merge entity @e[type=minecraft:villager,limit=1,sort=nearest] {CustomName:"Celestial"} | F61: ="/tag @e[type=minecraft:villager,name="""&B61&""",limit=1] add npc_"&SUBSTITUTE(LOWER(B61)," ","_") -> /tag @e[type=minecraft:villager,name="Celestial",limit=1] add npc_celestial | G61: =B61 -> Celestial | H61: =MID(F61,I61+4,99) -> npc_celestial | I61: =FIND("add npc",F61) -> 59
A62: Jhelom | B62: Smirk | C62: Smirk: proprietor of The Inn of Ends | E62: ="/data merge entity @e[type=minecraft:villager,limit=1,sort=nearest] {CustomName:"""&B62&"""}" -> /data merge entity @e[type=minecraft:villager,limit=1,sort=nearest] {CustomName:"Smirk"} | F62: ="/tag @e[type=minecraft:villager,name="""&B62&""",limit=1] add npc_"&SUBSTITUTE(LOWER(B62)," ","_") -> /tag @e[type=minecraft:villager,name="Smirk",limit=1] add npc_smirk | G62: =B62 -> Smirk | H62: =MID(F62,I62+4,99) -> npc_smirk | I62: =FIND("add npc",F62) -> 55
A63: Jhelom | B63: Triplet | C63: Triplet: proprietor of Heal and Health | E63: ="/data merge entity @e[type=minecraft:villager,limit=1,sort=nearest] {CustomName:"""&B63&"""}" -> /data merge entity @e[type=minecraft:villager,limit=1,sort=nearest] {CustomName:"Triplet"} | F63: ="/tag @e[type=minecraft:villager,name="""&B63&""",limit=1] add npc_"&SUBSTITUTE(LOWER(B63)," ","_") -> /tag @e[type=minecraft:villager,name="Triplet",limit=1] add npc_triplet | G63: =B63 -> Triplet | H63: =MID(F63,I63+4,99) -> npc_triplet | I63: =FIND("add npc",F63) -> 57
A64: Jhelom | B64: Valiant | C64: Valiant: proprietor of Valiant's Armour | E64: ="/data merge entity @e[type=minecraft:villager,limit=1,sort=nearest] {CustomName:"""&B64&"""}" -> /data merge entity @e[type=minecraft:villager,limit=1,sort=nearest] {CustomName:"Valiant"} | F64: ="/tag @e[type=minecraft:villager,name="""&B64&""",limit=1] add npc_"&SUBSTITUTE(LOWER(B64)," ","_") -> /tag @e[type=minecraft:villager,name="Valiant",limit=1] add npc_valiant | G64: =B64 -> Valiant | H64: =MID(F64,I64+4,99) -> npc_valiant | I64: =FIND("add npc",F64) -> 57
A65: Jhelom | B65: Willard | C65: Willard: proprietor of Willard's Weaponry | E65: ="/data merge entity @e[type=minecraft:villager,limit=1,sort=nearest] {CustomName:"""&B65&"""}" -> /data merge entity @e[type=minecraft:villager,limit=1,sort=nearest] {CustomName:"Willard"} | F65: ="/tag @e[type=minecraft:villager,name="""&B65&""",limit=1] add npc_"&SUBSTITUTE(LOWER(B65)," ","_") -> /tag @e[type=minecraft:villager,name="Willard",limit=1] add npc_willard | G65: =B65 -> Willard | H65: =MID(F65,I65+4,99) -> npc_willard | I65: =FIND("add npc",F65) -> 57
A66: Jhelom | B66: Jho Velkum | C66: Welcomer | D66: Librarian | E66: ="/data merge entity @e[type=minecraft:villager,limit=1,sort=nearest] {CustomName:"""&B66&"""}" -> /data merge entity @e[type=minecraft:villager,limit=1,sort=nearest] {CustomName:"Jho Velkum"} | F66: ="/tag @e[type=minecraft:villager,name="""&B66&""",limit=1] add npc_"&SUBSTITUTE(LOWER(B66)," ","_") -> /tag @e[type=minecraft:villager,name="Jho Velkum",limit=1] add npc_jho_velkum | G66: =B66 -> Jho Velkum | H66: =MID(F66,I66+4,99) -> npc_jho_velkum | I66: =FIND("add npc",F66) -> 60
A67: Jhelom | B67: Slithe | C67: =IF(ISNA(VLOOKUP(A67&"|"&B67&"|"&"LOOK",'NPC Dialogue'!$A:$F,6,FALSE)),VLOOKUP(A67&"|"&B67&"|"&"You see..",'NPC Dialogue'!$A:$F,6,FALSE),VLOOKUP(A67&"|"&B67&"|"&"LOOK",'NPC Dialogue'!$A:$F,6,FALSE)) -> A valiant warrior. | D67: Weaponsmith, in bed, In healing store. | E67: ="/data merge entity @e[type=minecraft:villager,limit=1,sort=nearest] {CustomName:"""&B67&"""}" -> /data merge entity @e[type=minecraft:villager,limit=1,sort=nearest] {CustomName:"Slithe"} | F67: ="/tag @e[type=minecraft:villager,name="""&B67&""",limit=1] add npc_"&SUBSTITUTE(LOWER(B67)," ","_") -> /tag @e[type=minecraft:villager,name="Slithe",limit=1] add npc_slithe | G67: =B67 -> Slithe | H67: =MID(F67,I67+4,99) -> npc_slithe | I67: =FIND("add npc",F67) -> 56
A68: Skara Brae | B68: Mintol | C68: Mintol: proprietor of Food for Thought | D68: Butcher | E68: ="/data merge entity @e[type=minecraft:villager,limit=1,sort=nearest] {CustomName:"""&B68&"""}" -> /data merge entity @e[type=minecraft:villager,limit=1,sort=nearest] {CustomName:"Mintol"} | F68: ="/tag @e[type=minecraft:villager,name="""&B68&""",limit=1] add npc_"&SUBSTITUTE(LOWER(B68)," ","_") -> /tag @e[type=minecraft:villager,name="Mintol",limit=1] add npc_mintol | G68: =B68 -> Mintol | H68: =MID(F68,I68+4,99) -> npc_mintol | I68: =FIND("add npc",F68) -> 56
A69: Skara Brae | B69: Sasha | C69: Sasha: proprietor of Herbs and Spice | D69: In Herbs shop | E69: ="/data merge entity @e[type=minecraft:villager,limit=1,sort=nearest] {CustomName:"""&B69&"""}" -> /data merge entity @e[type=minecraft:villager,limit=1,sort=nearest] {CustomName:"Sasha"} | F69: ="/tag @e[type=minecraft:villager,name="""&B69&""",limit=1] add npc_"&SUBSTITUTE(LOWER(B69)," ","_") -> /tag @e[type=minecraft:villager,name="Sasha",limit=1] add npc_sasha | G69: =B69 -> Sasha | H69: =MID(F69,I69+4,99) -> npc_sasha | I69: =FIND("add npc",F69) -> 55
A70: Skara Brae | B70: Spiran | C70: Spiran: proprietor of The Mystic Heal | D70: In HEALER shop | E70: ="/data merge entity @e[type=minecraft:villager,limit=1,sort=nearest] {CustomName:"""&B70&"""}" -> /data merge entity @e[type=minecraft:villager,limit=1,sort=nearest] {CustomName:"Spiran"} | F70: ="/tag @e[type=minecraft:villager,name="""&B70&""",limit=1] add npc_"&SUBSTITUTE(LOWER(B70)," ","_") -> /tag @e[type=minecraft:villager,name="Spiran",limit=1] add npc_spiran | G70: =B70 -> Spiran | H70: =MID(F70,I70+4,99) -> npc_spiran | I70: =FIND("add npc",F70) -> 56
A71: Skara Brae | B71: Tyrone | C71: Tyrone: proprietor of The Inn of the Spirits | E71: ="/data merge entity @e[type=minecraft:villager,limit=1,sort=nearest] {CustomName:"""&B71&"""}" -> /data merge entity @e[type=minecraft:villager,limit=1,sort=nearest] {CustomName:"Tyrone"} | F71: ="/tag @e[type=minecraft:villager,name="""&B71&""",limit=1] add npc_"&SUBSTITUTE(LOWER(B71)," ","_") -> /tag @e[type=minecraft:villager,name="Tyrone",limit=1] add npc_tyrone | G71: =B71 -> Tyrone | H71: =MID(F71,I71+4,99) -> npc_tyrone | I71: =FIND("add npc",F71) -> 56
A72: Skara Brae | B72: Thule | C72: Tool shoppe Proprietor | D72: Tool seller | E72: ="/data merge entity @e[type=minecraft:villager,limit=1,sort=nearest] {CustomName:"""&B72&"""}" -> /data merge entity @e[type=minecraft:villager,limit=1,sort=nearest] {CustomName:"Thule"} | F72: ="/tag @e[type=minecraft:villager,name="""&B72&""",limit=1] add npc_"&SUBSTITUTE(LOWER(B72)," ","_") -> /tag @e[type=minecraft:villager,name="Thule",limit=1] add npc_thule | G72: =B72 -> Thule | H72: =MID(F72,I72+4,99) -> npc_thule | I72: =FIND("add npc",F72) -> 55
A73: Skara Brae | B73: Ambule | C73: =IF(ISNA(VLOOKUP(A73&"|"&B73&"|"&"LOOK",'NPC Dialogue'!$A:$F,6,FALSE)),VLOOKUP(A73&"|"&B73&"|"&"You see..",'NPC Dialogue'!$A:$F,6,FALSE),VLOOKUP(A73&"|"&B73&"|"&"LOOK",'NPC Dialogue'!$A:$F,6,FALSE)) -> A grimy beggar. | D73: Butcher (begging outside herbs shop) | E73: ="/data merge entity @e[type=minecraft:villager,limit=1,sort=nearest] {CustomName:"""&B73&"""}" -> /data merge entity @e[type=minecraft:villager,limit=1,sort=nearest] {CustomName:"Ambule"} | F73: ="/tag @e[type=minecraft:villager,name="""&B73&""",limit=1] add npc_"&SUBSTITUTE(LOWER(B73)," ","_") -> /tag @e[type=minecraft:villager,name="Ambule",limit=1] add npc_ambule | G73: =B73 -> Ambule | H73: =MID(F73,I73+4,99) -> npc_ambule | I73: =FIND("add npc",F73) -> 56
A74: Skara Brae | B74: Barren | C74: A beekeeper | D74: Farmer; beekeeper | E74: ="/data merge entity @e[type=minecraft:villager,limit=1,sort=nearest] {CustomName:"""&B74&"""}" -> /data merge entity @e[type=minecraft:villager,limit=1,sort=nearest] {CustomName:"Barren"} | F74: ="/tag @e[type=minecraft:villager,name="""&B74&""",limit=1] add npc_"&SUBSTITUTE(LOWER(B74)," ","_") -> /tag @e[type=minecraft:villager,name="Barren",limit=1] add npc_barren | G74: =B74 -> Barren | H74: =MID(F74,I74+4,99) -> npc_barren | I74: =FIND("add npc",F74) -> 56
A75: Skara Brae | B75: Emerson | C75: =IF(ISNA(VLOOKUP(A75&"|"&B75&"|"&"LOOK",'NPC Dialogue'!$A:$F,6,FALSE)),VLOOKUP(A75&"|"&B75&"|"&"You see..",'NPC Dialogue'!$A:$F,6,FALSE),VLOOKUP(A75&"|"&B75&"|"&"LOOK",'NPC Dialogue'!$A:$F,6,FALSE)) -> An injured man. | D75: In Healers. A leathermaker. | E75: ="/data merge entity @e[type=minecraft:villager,limit=1,sort=nearest] {CustomName:"""&B75&"""}" -> /data merge entity @e[type=minecraft:villager,limit=1,sort=nearest] {CustomName:"Emerson"} | F75: ="/tag @e[type=minecraft:villager,name="""&B75&""",limit=1] add npc_"&SUBSTITUTE(LOWER(B75)," ","_") -> /tag @e[type=minecraft:villager,name="Emerson",limit=1] add npc_emerson | G75: =B75 -> Emerson | H75: =MID(F75,I75+4,99) -> npc_emerson | I75: =FIND("add npc",F75) -> 57
A76: Skara Brae | B76: Granted | C76: =IF(ISNA(VLOOKUP(A76&"|"&B76&"|"&"LOOK",'NPC Dialogue'!$A:$F,6,FALSE)),VLOOKUP(A76&"|"&B76&"|"&"You see..",'NPC Dialogue'!$A:$F,6,FALSE),VLOOKUP(A76&"|"&B76&"|"&"LOOK",'NPC Dialogue'!$A:$F,6,FALSE)) -> A hungry beggar. | D76: Butcher; begs outside town near herbs shop | E76: ="/data merge entity @e[type=minecraft:villager,limit=1,sort=nearest] {CustomName:"""&B76&"""}" -> /data merge entity @e[type=minecraft:villager,limit=1,sort=nearest] {CustomName:"Granted"} | F76: ="/tag @e[type=minecraft:villager,name="""&B76&""",limit=1] add npc_"&SUBSTITUTE(LOWER(B76)," ","_") -> /tag @e[type=minecraft:villager,name="Granted",limit=1] add npc_granted | G76: =B76 -> Granted | H76: =MID(F76,I76+4,99) -> npc_granted | I76: =FIND("add npc",F76) -> 57
A77: Skara Brae | B77: Isaac | C77: =IF(ISNA(VLOOKUP(A77&"|"&B77&"|"&"LOOK",'NPC Dialogue'!$A:$F,6,FALSE)),VLOOKUP(A77&"|"&B77&"|"&"You see..",'NPC Dialogue'!$A:$F,6,FALSE),VLOOKUP(A77&"|"&B77&"|"&"LOOK",'NPC Dialogue'!$A:$F,6,FALSE)) -> A ghostly figure | D77: Disembodied Voice in Inn (maybe a nitwit, hidden somewhere?) | E77: ="/data merge entity @e[type=minecraft:villager,limit=1,sort=nearest] {CustomName:"""&B77&"""}" -> /data merge entity @e[type=minecraft:villager,limit=1,sort=nearest] {CustomName:"Isaac"} | F77: ="/tag @e[type=minecraft:villager,name="""&B77&""",limit=1] add npc_"&SUBSTITUTE(LOWER(B77)," ","_") -> /tag @e[type=minecraft:villager,name="Isaac",limit=1] add npc_isaac | G77: =B77 -> Isaac | H77: =MID(F77,I77+4,99) -> npc_isaac | I77: =FIND("add npc",F77) -> 55
A78: Skara Brae | B78: Presto | C78: =IF(ISNA(VLOOKUP(A78&"|"&B78&"|"&"LOOK",'NPC Dialogue'!$A:$F,6,FALSE)),VLOOKUP(A78&"|"&B78&"|"&"You see..",'NPC Dialogue'!$A:$F,6,FALSE),VLOOKUP(A78&"|"&B78&"|"&"LOOK",'NPC Dialogue'!$A:$F,6,FALSE)) -> A very small wizard. | D78: In herbs shop (buying) | E78: ="/data merge entity @e[type=minecraft:villager,limit=1,sort=nearest] {CustomName:"""&B78&"""}" -> /data merge entity @e[type=minecraft:villager,limit=1,sort=nearest] {CustomName:"Presto"} | F78: ="/tag @e[type=minecraft:villager,name="""&B78&""",limit=1] add npc_"&SUBSTITUTE(LOWER(B78)," ","_") -> /tag @e[type=minecraft:villager,name="Presto",limit=1] add npc_presto | G78: =B78 -> Presto | H78: =MID(F78,I78+4,99) -> npc_presto | I78: =FIND("add npc",F78) -> 56
A79: Skara Brae | B79: Romasco | C79: =IF(ISNA(VLOOKUP(A79&"|"&B79&"|"&"LOOK",'NPC Dialogue'!$A:$F,6,FALSE)),VLOOKUP(A79&"|"&B79&"|"&"You see..",'NPC Dialogue'!$A:$F,6,FALSE),VLOOKUP(A79&"|"&B79&"|"&"LOOK",'NPC Dialogue'!$A:$F,6,FALSE)) -> A short dumpy man with a book. | D79: In healer shop (buying); a librarian | E79: ="/data merge entity @e[type=minecraft:villager,limit=1,sort=nearest] {CustomName:"""&B79&"""}" -> /data merge entity @e[type=minecraft:villager,limit=1,sort=nearest] {CustomName:"Romasco"} | F79: ="/tag @e[type=minecraft:villager,name="""&B79&""",limit=1] add npc_"&SUBSTITUTE(LOWER(B79)," ","_") -> /tag @e[type=minecraft:villager,name="Romasco",limit=1] add npc_romasco | G79: =B79 -> Romasco | H79: =MID(F79,I79+4,99) -> npc_romasco | I79: =FIND("add npc",F79) -> 57
A80: Skara Brae | B80: Santayana | C80: =IF(ISNA(VLOOKUP(A80&"|"&B80&"|"&"LOOK",'NPC Dialogue'!$A:$F,6,FALSE)),VLOOKUP(A80&"|"&B80&"|"&"You see..",'NPC Dialogue'!$A:$F,6,FALSE),VLOOKUP(A80&"|"&B80&"|"&"LOOK",'NPC Dialogue'!$A:$F,6,FALSE)) -> A tall ranger. | D80: In Food shoppe; Cartographer | E80: ="/data merge entity @e[type=minecraft:villager,limit=1,sort=nearest] {CustomName:"""&B80&"""}" -> /data merge entity @e[type=minecraft:villager,limit=1,sort=nearest] {CustomName:"Santayana"} | F80: ="/tag @e[type=minecraft:villager,name="""&B80&""",limit=1] add npc_"&SUBSTITUTE(LOWER(B80)," ","_") -> /tag @e[type=minecraft:villager,name="Santayana",limit=1] add npc_santayana | G80: =B80 -> Santayana | H80: =MID(F80,I80+4,99) -> npc_santayana | I80: =FIND("add npc",F80) -> 59
A81: Skara Brae | B81: Shamino | C81: =IF(ISNA(VLOOKUP(A81&"|"&B81&"|"&"LOOK",'NPC Dialogue'!$A:$F,6,FALSE)),VLOOKUP(A81&"|"&B81&"|"&"You see..",'NPC Dialogue'!$A:$F,6,FALSE),VLOOKUP(A81&"|"&B81&"|"&"LOOK",'NPC Dialogue'!$A:$F,6,FALSE)) -> A solemn ranger. | D81: Welcomer | E81: ="/data merge entity @e[type=minecraft:villager,limit=1,sort=nearest] {CustomName:"""&B81&"""}" -> /data merge entity @e[type=minecraft:villager,limit=1,sort=nearest] {CustomName:"Shamino"} | F81: ="/tag @e[type=minecraft:villager,name="""&B81&""",limit=1] add npc_"&SUBSTITUTE(LOWER(B81)," ","_") -> /tag @e[type=minecraft:villager,name="Shamino",limit=1] add npc_shamino | G81: =B81 -> Shamino | H81: =MID(F81,I81+4,99) -> npc_shamino | I81: =FIND("add npc",F81) -> 57
A82: Minoc | B82: Alex | C82: =IF(ISNA(VLOOKUP(A82&"|"&B82&"|"&"LOOK",'NPC Dialogue'!$A:$F,6,FALSE)),VLOOKUP(A82&"|"&B82&"|"&"You see..",'NPC Dialogue'!$A:$F,6,FALSE),VLOOKUP(A82&"|"&B82&"|"&"LOOK",'NPC Dialogue'!$A:$F,6,FALSE)) -> A nitwit with flowers. | D82: Nitwit | E82: ="/data merge entity @e[type=minecraft:villager,limit=1,sort=nearest] {CustomName:"""&B82&"""}" -> /data merge entity @e[type=minecraft:villager,limit=1,sort=nearest] {CustomName:"Alex"} | F82: ="/tag @e[type=minecraft:villager,name="""&B82&""",limit=1] add npc_"&SUBSTITUTE(LOWER(B82)," ","_") -> /tag @e[type=minecraft:villager,name="Alex",limit=1] add npc_alex | G82: =B82 -> Alex | H82: =MID(F82,I82+4,99) -> npc_alex | I82: =FIND("add npc",F82) -> 54
A83: Minoc | B83: Azure | C83: =IF(ISNA(VLOOKUP(A83&"|"&B83&"|"&"LOOK",'NPC Dialogue'!$A:$F,6,FALSE)),VLOOKUP(A83&"|"&B83&"|"&"You see..",'NPC Dialogue'!$A:$F,6,FALSE),VLOOKUP(A83&"|"&B83&"|"&"LOOK",'NPC Dialogue'!$A:$F,6,FALSE)) -> A tinker at the table. | D83: At the inn; a toolsmith | E83: ="/data merge entity @e[type=minecraft:villager,limit=1,sort=nearest] {CustomName:"""&B83&"""}" -> /data merge entity @e[type=minecraft:villager,limit=1,sort=nearest] {CustomName:"Azure"} | F83: ="/tag @e[type=minecraft:villager,name="""&B83&""",limit=1] add npc_"&SUBSTITUTE(LOWER(B83)," ","_") -> /tag @e[type=minecraft:villager,name="Azure",limit=1] add npc_azure | G83: =B83 -> Azure | H83: =MID(F83,I83+4,99) -> npc_azure | I83: =FIND("add npc",F83) -> 55
A84: Minoc | B84: Bob the Beggar | C84: =IF(ISNA(VLOOKUP(A84&"|"&B84&"|"&"LOOK",'NPC Dialogue'!$A:$F,6,FALSE)),VLOOKUP(A84&"|"&B84&"|"&"You see..",'NPC Dialogue'!$A:$F,6,FALSE),VLOOKUP(A84&"|"&B84&"|"&"LOOK",'NPC Dialogue'!$A:$F,6,FALSE)) -> A sickly little man. | E84: ="/data merge entity @e[type=minecraft:villager,limit=1,sort=nearest] {CustomName:"""&B84&"""}" -> /data merge entity @e[type=minecraft:villager,limit=1,sort=nearest] {CustomName:"Bob the Beggar"} | F84: ="/tag @e[type=minecraft:villager,name="""&B84&""",limit=1] add npc_"&SUBSTITUTE(LOWER(B84)," ","_") -> /tag @e[type=minecraft:villager,name="Bob the Beggar",limit=1] add npc_bob_the_beggar | G84: =B84 -> Bob the Beggar | H84: =MID(F84,I84+4,99) -> npc_bob_the_beggar | I84: =FIND("add npc",F84) -> 64
A85: Minoc | B85: Damon | C85: =IF(ISNA(VLOOKUP(A85&"|"&B85&"|"&"LOOK",'NPC Dialogue'!$A:$F,6,FALSE)),VLOOKUP(A85&"|"&B85&"|"&"You see..",'NPC Dialogue'!$A:$F,6,FALSE),VLOOKUP(A85&"|"&B85&"|"&"LOOK",'NPC Dialogue'!$A:$F,6,FALSE)) -> A meek shepherd. | E85: ="/data merge entity @e[type=minecraft:villager,limit=1,sort=nearest] {CustomName:"""&B85&"""}" -> /data merge entity @e[type=minecraft:villager,limit=1,sort=nearest] {CustomName:"Damon"} | F85: ="/tag @e[type=minecraft:villager,name="""&B85&""",limit=1] add npc_"&SUBSTITUTE(LOWER(B85)," ","_") -> /tag @e[type=minecraft:villager,name="Damon",limit=1] add npc_damon | G85: =B85 -> Damon | H85: =MID(F85,I85+4,99) -> npc_damon | I85: =FIND("add npc",F85) -> 55
A86: Minoc | B86: Gimble | C86: =IF(ISNA(VLOOKUP(A86&"|"&B86&"|"&"LOOK",'NPC Dialogue'!$A:$F,6,FALSE)),VLOOKUP(A86&"|"&B86&"|"&"You see..",'NPC Dialogue'!$A:$F,6,FALSE),VLOOKUP(A86&"|"&B86&"|"&"LOOK",'NPC Dialogue'!$A:$F,6,FALSE)) -> A fading man. | D86: Nitwit | E86: ="/data merge entity @e[type=minecraft:villager,limit=1,sort=nearest] {CustomName:"""&B86&"""}" -> /data merge entity @e[type=minecraft:villager,limit=1,sort=nearest] {CustomName:"Gimble"} | F86: ="/tag @e[type=minecraft:villager,name="""&B86&""",limit=1] add npc_"&SUBSTITUTE(LOWER(B86)," ","_") -> /tag @e[type=minecraft:villager,name="Gimble",limit=1] add npc_gimble | G86: =B86 -> Gimble | H86: =MID(F86,I86+4,99) -> npc_gimble | I86: =FIND("add npc",F86) -> 56
A87: Minoc | B87: Jude | C87: =IF(ISNA(VLOOKUP(A87&"|"&B87&"|"&"LOOK",'NPC Dialogue'!$A:$F,6,FALSE)),VLOOKUP(A87&"|"&B87&"|"&"You see..",'NPC Dialogue'!$A:$F,6,FALSE),VLOOKUP(A87&"|"&B87&"|"&"LOOK",'NPC Dialogue'!$A:$F,6,FALSE)) -> A ragged soul. | E87: ="/data merge entity @e[type=minecraft:villager,limit=1,sort=nearest] {CustomName:"""&B87&"""}" -> /data merge entity @e[type=minecraft:villager,limit=1,sort=nearest] {CustomName:"Jude"} | F87: ="/tag @e[type=minecraft:villager,name="""&B87&""",limit=1] add npc_"&SUBSTITUTE(LOWER(B87)," ","_") -> /tag @e[type=minecraft:villager,name="Jude",limit=1] add npc_jude | G87: =B87 -> Jude | H87: =MID(F87,I87+4,99) -> npc_jude | I87: =FIND("add npc",F87) -> 54
A88: Minoc | B88: Julia | C88: =IF(ISNA(VLOOKUP(A88&"|"&B88&"|"&"LOOK",'NPC Dialogue'!$A:$F,6,FALSE)),VLOOKUP(A88&"|"&B88&"|"&"You see..",'NPC Dialogue'!$A:$F,6,FALSE),VLOOKUP(A88&"|"&B88&"|"&"LOOK",'NPC Dialogue'!$A:$F,6,FALSE)) -> An agile tinker. | E88: ="/data merge entity @e[type=minecraft:villager,limit=1,sort=nearest] {CustomName:"""&B88&"""}" -> /data merge entity @e[type=minecraft:villager,limit=1,sort=nearest] {CustomName:"Julia"} | F88: ="/tag @e[type=minecraft:villager,name="""&B88&""",limit=1] add npc_"&SUBSTITUTE(LOWER(B88)," ","_") -> /tag @e[type=minecraft:villager,name="Julia",limit=1] add npc_julia | G88: =B88 -> Julia | H88: =MID(F88,I88+4,99) -> npc_julia | I88: =FIND("add npc",F88) -> 55
A89: Minoc | B89: Merida | C89: =IF(ISNA(VLOOKUP(A89&"|"&B89&"|"&"LOOK",'NPC Dialogue'!$A:$F,6,FALSE)),VLOOKUP(A89&"|"&B89&"|"&"You see..",'NPC Dialogue'!$A:$F,6,FALSE),VLOOKUP(A89&"|"&B89&"|"&"LOOK",'NPC Dialogue'!$A:$F,6,FALSE)) -> A wandering tinker. | E89: ="/data merge entity @e[type=minecraft:villager,limit=1,sort=nearest] {CustomName:"""&B89&"""}" -> /data merge entity @e[type=minecraft:villager,limit=1,sort=nearest] {CustomName:"Merida"} | F89: ="/tag @e[type=minecraft:villager,name="""&B89&""",limit=1] add npc_"&SUBSTITUTE(LOWER(B89)," ","_") -> /tag @e[type=minecraft:villager,name="Merida",limit=1] add npc_merida | G89: =B89 -> Merida | H89: =MID(F89,I89+4,99) -> npc_merida | I89: =FIND("add npc",F89) -> 56
A90: Minoc | B90: Mike Ward | C90: =IF(ISNA(VLOOKUP(A90&"|"&B90&"|"&"LOOK",'NPC Dialogue'!$A:$F,6,FALSE)),VLOOKUP(A90&"|"&B90&"|"&"You see..",'NPC Dialogue'!$A:$F,6,FALSE),VLOOKUP(A90&"|"&B90&"|"&"LOOK",'NPC Dialogue'!$A:$F,6,FALSE)) -> A stocky ranger. | E90: ="/data merge entity @e[type=minecraft:villager,limit=1,sort=nearest] {CustomName:"""&B90&"""}" -> /data merge entity @e[type=minecraft:villager,limit=1,sort=nearest] {CustomName:"Mike Ward"} | F90: ="/tag @e[type=minecraft:villager,name="""&B90&""",limit=1] add npc_"&SUBSTITUTE(LOWER(B90)," ","_") -> /tag @e[type=minecraft:villager,name="Mike Ward",limit=1] add npc_mike_ward | G90: =B90 -> Mike Ward | H90: =MID(F90,I90+4,99) -> npc_mike_ward | I90: =FIND("add npc",F90) -> 59
A91: Minoc | B91: Mischief | C91: =IF(ISNA(VLOOKUP(A91&"|"&B91&"|"&"LOOK",'NPC Dialogue'!$A:$F,6,FALSE)),VLOOKUP(A91&"|"&B91&"|"&"You see..",'NPC Dialogue'!$A:$F,6,FALSE),VLOOKUP(A91&"|"&B91&"|"&"LOOK",'NPC Dialogue'!$A:$F,6,FALSE)) -> A happy tinker. | E91: ="/data merge entity @e[type=minecraft:villager,limit=1,sort=nearest] {CustomName:"""&B91&"""}" -> /data merge entity @e[type=minecraft:villager,limit=1,sort=nearest] {CustomName:"Mischief"} | F91: ="/tag @e[type=minecraft:villager,name="""&B91&""",limit=1] add npc_"&SUBSTITUTE(LOWER(B91)," ","_") -> /tag @e[type=minecraft:villager,name="Mischief",limit=1] add npc_mischief | G91: =B91 -> Mischief | H91: =MID(F91,I91+4,99) -> npc_mischief | I91: =FIND("add npc",F91) -> 58
A92: Minoc | B92: Shentis | C92: =IF(ISNA(VLOOKUP(A92&"|"&B92&"|"&"LOOK",'NPC Dialogue'!$A:$F,6,FALSE)),VLOOKUP(A92&"|"&B92&"|"&"You see..",'NPC Dialogue'!$A:$F,6,FALSE),VLOOKUP(A92&"|"&B92&"|"&"LOOK",'NPC Dialogue'!$A:$F,6,FALSE)) -> A rotund tinker. | D92: Welcomer; Toolsmith | E92: ="/data merge entity @e[type=minecraft:villager,limit=1,sort=nearest] {CustomName:"""&B92&"""}" -> /data merge entity @e[type=minecraft:villager,limit=1,sort=nearest] {CustomName:"Shentis"} | F92: ="/tag @e[type=minecraft:villager,name="""&B92&""",limit=1] add npc_"&SUBSTITUTE(LOWER(B92)," ","_") -> /tag @e[type=minecraft:villager,name="Shentis",limit=1] add npc_shentis | G92: =B92 -> Shentis | H92: =MID(F92,I92+4,99) -> npc_shentis | I92: =FIND("add npc",F92) -> 57
A93: Minoc | B93: Singsong | C93: =IF(ISNA(VLOOKUP(A93&"|"&B93&"|"&"LOOK",'NPC Dialogue'!$A:$F,6,FALSE)),VLOOKUP(A93&"|"&B93&"|"&"You see..",'NPC Dialogue'!$A:$F,6,FALSE),VLOOKUP(A93&"|"&B93&"|"&"LOOK",'NPC Dialogue'!$A:$F,6,FALSE)) -> A cute bard. | D93: shepherd | E93: ="/data merge entity @e[type=minecraft:villager,limit=1,sort=nearest] {CustomName:"""&B93&"""}" -> /data merge entity @e[type=minecraft:villager,limit=1,sort=nearest] {CustomName:"Singsong"} | F93: ="/tag @e[type=minecraft:villager,name="""&B93&""",limit=1] add npc_"&SUBSTITUTE(LOWER(B93)," ","_") -> /tag @e[type=minecraft:villager,name="Singsong",limit=1] add npc_singsong | G93: =B93 -> Singsong | H93: =MID(F93,I93+4,99) -> npc_singsong | I93: =FIND("add npc",F93) -> 58
A94: Minoc | B94: Zircon | C94: =IF(ISNA(VLOOKUP(A94&"|"&B94&"|"&"LOOK",'NPC Dialogue'!$A:$F,6,FALSE)),VLOOKUP(A94&"|"&B94&"|"&"You see..",'NPC Dialogue'!$A:$F,6,FALSE),VLOOKUP(A94&"|"&B94&"|"&"LOOK",'NPC Dialogue'!$A:$F,6,FALSE)) -> A seasoned blacksmith. | E94: ="/data merge entity @e[type=minecraft:villager,limit=1,sort=nearest] {CustomName:"""&B94&"""}" -> /data merge entity @e[type=minecraft:villager,limit=1,sort=nearest] {CustomName:"Zircon"} | F94: ="/tag @e[type=minecraft:villager,name="""&B94&""",limit=1] add npc_"&SUBSTITUTE(LOWER(B94)," ","_") -> /tag @e[type=minecraft:villager,name="Zircon",limit=1] add npc_zircon | G94: =B94 -> Zircon | H94: =MID(F94,I94+4,99) -> npc_zircon | I94: =FIND("add npc",F94) -> 56
A95: Minoc | B95: Estro | C95: Proprietor of the Inn | E95: ="/data merge entity @e[type=minecraft:villager,limit=1,sort=nearest] {CustomName:"""&B95&"""}" -> /data merge entity @e[type=minecraft:villager,limit=1,sort=nearest] {CustomName:"Estro"} | F95: ="/tag @e[type=minecraft:villager,name="""&B95&""",limit=1] add npc_"&SUBSTITUTE(LOWER(B95)," ","_") -> /tag @e[type=minecraft:villager,name="Estro",limit=1] add npc_estro | G95: =B95 -> Estro | H95: =MID(F95,I95+4,99) -> npc_estro | I95: =FIND("add npc",F95) -> 55
A96: Minoc | B96: Peter | C96: Proprietor of the Iron Works | D96: Toosmith | E96: ="/data merge entity @e[type=minecraft:villager,limit=1,sort=nearest] {CustomName:"""&B96&"""}" -> /data merge entity @e[type=minecraft:villager,limit=1,sort=nearest] {CustomName:"Peter"} | F96: ="/tag @e[type=minecraft:villager,name="""&B96&""",limit=1] add npc_"&SUBSTITUTE(LOWER(B96)," ","_") -> /tag @e[type=minecraft:villager,name="Peter",limit=1] add npc_peter | G96: =B96 -> Peter | H96: =MID(F96,I96+4,99) -> npc_peter | I96: =FIND("add npc",F96) -> 55
A97: Minoc | B97: Butch | C97: Chef of the Inn | D97: Butcher | E97: ="/data merge entity @e[type=minecraft:villager,limit=1,sort=nearest] {CustomName:"""&B97&"""}" -> /data merge entity @e[type=minecraft:villager,limit=1,sort=nearest] {CustomName:"Butch"} | F97: ="/tag @e[type=minecraft:villager,name="""&B97&""",limit=1] add npc_"&SUBSTITUTE(LOWER(B97)," ","_") -> /tag @e[type=minecraft:villager,name="Butch",limit=1] add npc_butch | G97: =B97 -> Butch | H97: =MID(F97,I97+4,99) -> npc_butch | I97: =FIND("add npc",F97) -> 55
A98: Minoc | B98: Pierre | C98: Weapon seller | D98: Weaponsmith | E98: ="/data merge entity @e[type=minecraft:villager,limit=1,sort=nearest] {CustomName:"""&B98&"""}" -> /data merge entity @e[type=minecraft:villager,limit=1,sort=nearest] {CustomName:"Pierre"} | F98: ="/tag @e[type=minecraft:villager,name="""&B98&""",limit=1] add npc_"&SUBSTITUTE(LOWER(B98)," ","_") -> /tag @e[type=minecraft:villager,name="Pierre",limit=1] add npc_pierre | G98: =B98 -> Pierre | H98: =MID(F98,I98+4,99) -> npc_pierre | I98: =FIND("add npc",F98) -> 56
A99: Minoc | B99: Piedro | C99: Armor seller | D99: Armorer | E99: ="/data merge entity @e[type=minecraft:villager,limit=1,sort=nearest] {CustomName:"""&B99&"""}" -> /data merge entity @e[type=minecraft:villager,limit=1,sort=nearest] {CustomName:"Piedro"} | F99: ="/tag @e[type=minecraft:villager,name="""&B99&""",limit=1] add npc_"&SUBSTITUTE(LOWER(B99)," ","_") -> /tag @e[type=minecraft:villager,name="Piedro",limit=1] add npc_piedro | G99: =B99 -> Piedro | H99: =MID(F99,I99+4,99) -> npc_piedro | I99: =FIND("add npc",F99) -> 56
A100: Britain | B100: Celest | C100: =IF(ISNA(VLOOKUP(A100&"|"&B100&"|"&"LOOK",'NPC Dialogue'!$A:$F,6,FALSE)),VLOOKUP(A100&"|"&B100&"|"&"You see..",'NPC Dialogue'!$A:$F,6,FALSE),VLOOKUP(A100&"|"&B100&"|"&"LOOK",'NPC Dialogue'!$A:$F,6,FALSE)) -> #N/A | E100: ="/data merge entity @e[type=minecraft:villager,limit=1,sort=nearest] {CustomName:"""&B100&"""}" -> /data merge entity @e[type=minecraft:villager,limit=1,sort=nearest] {CustomName:"Celest"} | F100: ="/tag @e[type=minecraft:villager,name="""&B100&""",limit=1] add npc_"&SUBSTITUTE(LOWER(B100)," ","_") -> /tag @e[type=minecraft:villager,name="Celest",limit=1] add npc_celest | G100: =B100 -> Celest | H100: =MID(F100,I100+4,99) -> npc_celest | I100: =FIND("add npc",F100) -> 56
A101: Britain | B101: Child | C101: =IF(ISNA(VLOOKUP(A101&"|"&B101&"|"&"LOOK",'NPC Dialogue'!$A:$F,6,FALSE)),VLOOKUP(A101&"|"&B101&"|"&"You see..",'NPC Dialogue'!$A:$F,6,FALSE),VLOOKUP(A101&"|"&B101&"|"&"LOOK",'NPC Dialogue'!$A:$F,6,FALSE)) -> A small child | E101: ="/data merge entity @e[type=minecraft:villager,limit=1,sort=nearest] {CustomName:"""&B101&"""}" -> /data merge entity @e[type=minecraft:villager,limit=1,sort=nearest] {CustomName:"Child"} | F101: ="/tag @e[type=minecraft:villager,name="""&B101&""",limit=1] add npc_"&SUBSTITUTE(LOWER(B101)," ","_") -> /tag @e[type=minecraft:villager,name="Child",limit=1] add npc_child | G101: =B101 -> Child | H101: =MID(F101,I101+4,99) -> npc_child | I101: =FIND("add npc",F101) -> 55
A102: Britain | B102: Cricket | C102: =IF(ISNA(VLOOKUP(A102&"|"&B102&"|"&"LOOK",'NPC Dialogue'!$A:$F,6,FALSE)),VLOOKUP(A102&"|"&B102&"|"&"You see..",'NPC Dialogue'!$A:$F,6,FALSE),VLOOKUP(A102&"|"&B102&"|"&"LOOK",'NPC Dialogue'!$A:$F,6,FALSE)) -> A bard in green | E102: ="/data merge entity @e[type=minecraft:villager,limit=1,sort=nearest] {CustomName:"""&B102&"""}" -> /data merge entity @e[type=minecraft:villager,limit=1,sort=nearest] {CustomName:"Cricket"} | F102: ="/tag @e[type=minecraft:villager,name="""&B102&""",limit=1] add npc_"&SUBSTITUTE(LOWER(B102)," ","_") -> /tag @e[type=minecraft:villager,name="Cricket",limit=1] add npc_cricket | G102: =B102 -> Cricket | H102: =MID(F102,I102+4,99) -> npc_cricket | I102: =FIND("add npc",F102) -> 57
...

Sheet gameDesignMisc
C3: Trinsic | D3: Lexington | E3: QUES | F3: The solving of quests brings ye honor! | G3: add this to game for HONOR scoreboard (for various mini-quests, in-game)
C4: Trinsic | D4: Skitle | E4: STON | F4: I have seen the purple stone used in the altars of truth and courage! | G4: this is U4's mechanic for needing to know how the colors matter.
C5: Trinsic | D5: Terrin | E5: What am I up to? | F5: I had been looking for the rune when a skeleton appeared! | G5: For random, non-magenta shulkers, there's a 20% chance a skeleton will pop out! For the black one, there's a wither skeleton egg and wither may also pop out…?
C8: Jhelom | G8: Has 1-2 of the three metallurgists
C10: Lycaeum | G10: In the library there is one bookshelf which looks different -- 4.N.(4,8).2.1 -- it's missing a book. If you look to the right on floor thru grating you'll find a grey shulker box containing the missing book
C11: Minoc | F11: No Trades set up yet in Minoc -- remember to add Fire Protection Potion to one of them! (to retrieve rune from forge)
B13: We'll have to put these Vesperian clues into other towns:
C14: Villages | D14: Vesper | E14: Gem | F14: MANT | G14: Since humility is the opposite of pride, so is its mantra!
C15: Villages | D15: Vesper | E15: Plain | F15: HUMI | G15: When the 3 principles of virtue combine in eight ways pride has no virtue!

Sheet UsefulTagCmds
A1: Tagging Villagers as NPCs
A2: -------------------------
A3: /data merge entity @e[type=minecraft:villager,limit=1,sort=nearest] {CustomName:"Sasha"}
A4: /tag @e[type=minecraft:villager,name="Tyrone",limit=1] add npc_sasha
A7: REMOVING TAGS APPLIED INCORRECTLY:
A8: /tag @e[type=minecraft:villager,name="Mariah",limit=1] remove npc_shazom
A10: -----------------
A11: Make a villager a NITWIT:
A13: /data merge entity @e[type=minecraft:villager,limit=1,sort=nearest] {VillagerData:{profession:"minecraft:nitwit"}}

Sheet Runes_Stones_Mantras
A1: category | B1: virtue_or_color | C1: location(s) | D1: how_to_obtain_chain | E1: answer
A2: Rune | B2: Honesty | C2: Moonglow | D2: Christen ("My friend William knows where the rune of honesty is.") -> William ("Search for the rune of honesty by Mariah's gold!") | E2: Search by Mariah's gold, in Moonglow
A3: Rune | B3: Compassion | C3: Britain | D3: Sprite, if given help/food ("In return I shall tell thee that Pepper knows of the rune!") -> Pepper ("The rune of compassion lies at the end of a hall somewhere in this towne.") | E3: End of a hall somewhere in Britain
A4: Rune | B4: Valor | C4: Jhelom | D4: Lord Robert, if answered YES ("Thou dost deserve the rune, ask Nostro!") -> Nostro ("The rune is buried in a tower!") | E4: Buried in a tower in Jhelom
A5: Rune | B5: Sacrifice | C5: Minoc | D5: Gimble, if given a coin ("Remember Azure knows of the rune!") -> Azure ("I carve runes for passage into the shrines!", SACR: "Ask my sister, Mischief.") -> Mischief ("The rune of sacrifice is hard to get. It lies within the fires of the forge!") | E5: Azure the tinker carves it; Mischief says it lies within the fires of the forge (Minoc)
A6: Rune | B6: Justice | C6: Yew | D6: Druid, answered NO to "Dost thou have the rune?" ("Ask Talfourd for he knows of the rune.") -> Talfourd ("It is hidden well!") | E6: Hidden well (no exact spot given) - ask Talfourd, the judge, in Yew
A7: Rune | B7: Honor | C7: Trinsic | D7: Kline ("A man named Winthrop knows of the rune!") -> Winthrop ("There is a small child who knew named... Terrin.") -> Terrin ("It is buried in the southwest corner of towne.") | E7: Buried in the southwest corner of Trinsic
A8: Rune | B8: Spirituality | C8: Skara Brae / Castle Britannia | D8: Granted, if given food/money ("the ankh knows of the rune... my friend Ambule knows the mantra!") -> the Ankh of Spirituality (needs the mantra 'OM' spoken to it first -> "Search for the rune of spirituality in the treasure chamber of Britannia!") | E8: Treasure chamber of Castle Britannia (must know mantra OM first - see Mantras)
A9: Rune | B9: Humility | C9: Magincia / Paws | D9: Splot / Ruskin ("ask the snake of the rune...") -> Nate the Snake ("The sacred rune of humility was banished from this city. Ask Barren in Paws!") -> Barren, in Paws ("Search the hills in the south-east corner of town!") [Wheatpin also hints: "Around there in the nook of the mountains!"] | E9: South-east corner of Paws, in the hills/mountains
A10: Mantra | B10: Honesty | C10: Moonglow | D10: Cromwell states it directly: "The mantra of the shrine of honesty is 'AHM'." | E10: AHM
A11: Mantra | B11: Compassion | C11: Britain | D11: Child (quiz - answer NO: "Ask Cricket!") -> Cricket states it directly: "The mantra for the shrine of compassion is 'MU'!" | E11: MU
A12: Mantra | B12: Valor | C12: Jhelom | D12: Sir Hrothgar ("The mantra need be known, ask Aesop!") -> Aesop ("The mantra of valor is 'RA' use it in the shrine on the next isle!") | E12: RA
... A25: Stone | B25: Black | C25: Cove / a Moongate | D25: Nate the Snake ("Those who seek the black stone need ask at the pub in Britain!") -> Bartender in Pubs, for 20 gold ("the only one who knows where it lies is the wizard Merlin.") -> Merlin, in Cove ("The black stone is caught in a moon gate!... Stand where the gate of both moons dark shall appear. Search when the moons go dark!") | E25: Caught in a moongate when both moons are dark
A26: PreciousItem-MC

Sheet QuestionTriggers
A1: key | B1: town_type | C1: town_name | D1: npc_name | E1: trigger_word | F1: question
A2: =B2&"|"&C2&"|"&D2&"|"&E2 -> Castles|Castle Britannia|Chuckles|JEST | B2: Castles | C2: Castle Britannia | D2: Chuckles | E2: JEST | F2: Hast thou an ankh?
A3: =B3&"|"&C3&"|"&D3&"|"&E3 -> Castles|Castle Britannia|Gate Guard|CAST | B3: Castles | C3: Castle Britannia | D3: Gate Guard | E3: CAST | F3: Do you seek Lord British?
A4: =B4&"|"&C4&"|"&D4&"|"&E4 -> Castles|Castle Britannia|Treasury Guard|TREA | B4: Castles | C4: Castle Britannia | D4: Treasury Guard | E4: TREA | F4: Do you mean to steal?
A5: =B5&"|"&C5&"|"&D5&"|"&E5 -> Castles|Castle Britannia|Guard (2nd Floor)|GUAR | B5: Castles | C5: Castle Britannia | D5: Guard (2nd Floor) | E5: GUAR | F5: Art thou the most valiant warrior?
A6: =B6&"|"&C6&"|"&D6&"|"&E6 -> Castles|Castle Britannia|Jester Twins|BARD | B6: Castles | C6: Castle Britannia | D6: Jester Twins | E6: BARD | F6: Dost thou like the music?
A7: =B7&"|"&C7&"|"&D7&"|"&E7 -> Castles|Castle Britannia|Joshua|RIDD | B7: Castles | C7: Castle Britannia | D7: Joshua | E7: RIDD | F7: More?
A8: =B8&"|"&C8&"|"&D8&"|"&E8 -> Castles|Castle Britannia|Juliet|ONE | B8: Castles | C8: Castle Britannia | D8: Juliet | E8: ONE | F8: Know ye this?
A9: =B9&"|"&C9&"|"&D9&"|"&E9 -> Castles|Castle Britannia|Landri|PERI | B9: Castles | C9: Castle Britannia | D9: Landri | E9: PERI | F9: Wilt thou go on?
A10: =B10&"|"&C10&"|"&D10&"|"&E10 -> Castles|Castle Britannia|Le Chef|COOK | B10: Castles | C10: Castle Britannia | D10: Le Chef | E10: COOK | F10: Do you eat?
A11: =B11&"|"&C11&"|"&D11&"|"&E11 -> Castles|Castle Britannia|Prisoner|PRIS | B11: Castles | C11: Castle Britannia | D11: Prisoner | E11: PRIS | F11: Are you a pirate?
A12: =B12&"|"&C12&"|"&D12&"|"&E12 -> Castles|Castle Britannia|Reaper|THIN | B12: Castles | C12: Castle Britannia | D12: Reaper | E12: THIN | F12: Will you seek this thing?
A13: =B13&"|"&C13&"|"&D13&"|"&E13 -> Castles|Castle Britannia|Seesha|COUN | B13: Castles | C13: Castle Britannia | D13: Seesha | E13: COUN | F13: Fight ye for Britannia?
... A242: =B242&"|"&C242&"|"&D242&"|"&E242 -> Villages|Cove|Charm|AXIO | B242: Villages | C242: Cove | D242: Charm | E242: AXIO | F242: Know ye what they are?

Sheet MC-InterTownDependencies
A1: Town | B1: Needs | C1: Notes | D1: Town | E1: Has | F1: Notes
A2: Yew | B2: Oak Leaves (for druids/potions) | C2: L1 trade to bring in a lot of Oak Leaves unlocks JusticePotion | D2: <skara?> | E2: Hoe with Silk Touch

Sheet TheGypsy
A1: town_type | B1: town_name | C1: npc_name | D1: keyword | E1: reply
A2: Earth | B2: The Gypsy | C2: The Gypsy | D2: (intro) | E2: The Gypsy gives ethical challenges, to which the Stranger responds by choosing between two Virtues.
A3: Earth | B3: The Gypsy | C3: The Gypsy | D3: Honesty vs. Compassion | E3: Entrusted to deliver an uncounted purse of gold, thou dost meet a poor beggar. Dost thou A) deliver the gold knowing the Trust in thee was well-placed; or B) show Compassion, giving the Beggar a coin, knowing it won’t be missed?
A4: Earth | B4: The Gypsy | C4: The Gypsy | D4: Honesty vs. Valor | E4: Thou hast been prohibited by thy absent Lord from joining thy friends in a close pitched battle. Dost thou A) refrain, so thou may Honestly claim obedience; or B) show Valor, and aid thy comrades, knowing thou may deny it later?
A5: Earth | B5: The Gypsy | C5: The Gypsy | D5: Honesty vs. Justice | E5: A merchant owes thy friend money, now long past due. Thou dost see the same merchant drop a purse of gold. Dost thou A) Honestly return the purse intact; or B) Justly give thy friend a portion of the gold first?
A6: Earth | B6: The Gypsy | C6: The Gypsy | D6: Honesty vs. Sacrifice | E6: Thee and thy friend are valiant but penniless warriors. Thou both go out to slay a mighty dragon. Thy friend thinks he slew it, thee did. When asked, dost thou A) Truthfully claim the gold; or B) Allow thy friend the large reward?
A7: Earth | B7: The Gypsy | C7: The Gypsy | D7: Honesty vs. Honor | E7: Thou art sworn to protect thy Lord at any cost, yet thou knowest he hath committed a crime. Authorities ask thee of the affair, dost thou A) break thine oath by Honestly speaking; or B) uphold Honor by silently keeping thine oath?
A8: Earth | B8: The Gypsy | C8: The Gypsy | D8: Honesty vs. Spirituality | E8: Thy friend seeks admittance to thy Spiritual order. Thou art asked to vouch for his purity of Spirit, of which thou art unsure. Dost thou A) Honestly express thy doubt; or B) Vouch for him, hoping for his Spiritual improvement?
A9: Earth | B9: The Gypsy | C9: The Gypsy | D9: Honesty vs. Humility | E9: Thy Lord mistakenly believes he slew a dragon. Thou hast proof that thy lance felled the beast. When asked, dost thou A) Honestly claim the kill and the prize; or B) Humbly permit thy Lord his belief?
A10: Earth | B10: The Gypsy | C10: The Gypsy | D10: Compassion vs. Valor | E10: Thou dost manage to disarm thy mortal enemy in a duel. He is at thy mercy. Dost thou A) show Compassion by permitting him to yield; or B) slay him as expected of a Valiant duelist?
A11: Earth | B11: The Gypsy | C11: The Gypsy | D11: Compassion vs. Justice | E11: After 20 years thou hast found the slayer of thy best friends. The villain proves to be a man who provides the sole support for a young girl. Dost thou A) spare him in Compassion for the girl; or B) slay him in the name of Justice?
A12: Earth | B12: The Gypsy | C12: The Gypsy | D12: Compassion vs. Sacrifice | E12: Thee and thy friends have been routed and ordered to retreat. In defiance of thy orders, dost thou A) stop in Compassion to aid a wounded companion; or B) Sacrifice thyself to slow the pursuing enemy, so others can escape?
... A30: Earth | B30: The Gypsy | C30: The Gypsy | D30: Spirituality vs. Humility | E30: Thy parents wish thee to become an apprentice. Two positions are available. Dost thou A) Become an acolyte in the Spiritual order; or B) Become an assistant to a humble village cobbler?

Sheet Barkeeps
A1: town_type | B1: town_name | C1: npc_name | D1: keyword | E1: reply
A2: Towns | B2: ALL | C2: Bartender | D2: (intro) | E2: The bartender will give helpful advice if the Stranger overpays for ale.
A3: Towns | B3: Britain | C3: Bartender | D3: Black stone (20 gold) | E3: Ah, the Black Stone. Yes I’ve heard of it. But, the only one who knows where it lies is the wizard Merlin.
A4: Towns | B4: Jhelom | C4: Bartender | D4: Sextant (30 gold) | E4: For navigation a Sextant is vital... Ask for item "D" in the Guild shops!
A5: Towns | B5: Trinsic | C5: Bartender | D5: White stone (10 gold) | E5: Now let me see... Yes it was the old Hermit... Sloven! He is tough to find, lives near Lock Lake I hear.
A6: Villages | B6: Paws | C6: Bartender | D6: Mandrake (40 gold) | E6: The last person I knew that had any Mandrake was an old alchemist named Calumny.
A7: Villages | B7: Bucaneer's Den | C7: Bartender | D7: Skull (99 gold) | E7: If thou must know of that evilest of all things... find the beggar Jude. He is very very poor!
A8: Villages | B8: Vesper | C8: Bartender | D8: Nightshade (25 gold) | E8: Of Nightshade I know but this... Seek out Virgil or thou shalt miss! Try in Trinsic!
